{
"skeleton": { "hash": "C88BcjUmUpfw3Y7ndrzG8MyeoPk", "spine": "3.5.35", "width": 249.94, "height": 465.61 },
"bones": [
	{ "name": "root" },
	{ "name": "aitehua_61", "parent": "root", "length": 84.35, "rotation": 0.59, "x": 16.51, "y": 170.62 },
	{ "name": "aitehua_56", "parent": "aitehua_61", "length": 25.29, "rotation": 100.51, "x": 8.76, "y": 2.09 },
	{ "name": "aitehua_57", "parent": "aitehua_56", "length": 58.25, "rotation": 2.52, "x": 26.12, "y": -0.27 },
	{ "name": "aitehua_58", "parent": "aitehua_57", "length": 62.05, "rotation": -135.77, "x": 41.32, "y": -33.56 },
	{ "name": "aitehua_45", "parent": "aitehua_58", "length": 83.54, "rotation": 101.75, "x": 62.05 },
	{ "name": "aitehua_44", "parent": "aitehua_45", "length": 35.57, "rotation": 32.56, "x": 83.54 },
	{ "name": "aitehua_59", "parent": "aitehua_57", "length": 28.96, "rotation": -22.45, "x": 60.59, "y": -0.24 },
	{ "name": "aitehua_51", "parent": "aitehua_59", "length": 96.89, "rotation": -9.97, "x": 30.41, "y": 0.57 },
	{ "name": "aitehua_46", "parent": "aitehua_51", "length": 64.14, "rotation": 166.68, "x": 120.82, "y": 28.67 },
	{ "name": "aitehua_47", "parent": "aitehua_51", "length": 44.91, "rotation": -154.18, "x": 115.47, "y": -33.45 },
	{ "name": "aitehua_48", "parent": "aitehua_51", "length": 48.92, "rotation": -26.21, "x": 95.48, "y": 1.88 },
	{ "name": "aitehua_52", "parent": "aitehua_51", "length": 41.64, "rotation": 166.99, "x": -2.4, "y": 35.57 },
	{ "name": "aitehua_55", "parent": "aitehua_57", "length": 58.14, "rotation": 153.57, "x": 58.01, "y": 39.82 },
	{ "name": "aitehua_54", "parent": "aitehua_55", "length": 23.27, "rotation": 234.42, "x": 61.19, "y": -0.07 },
	{ "name": "aitehua_53", "parent": "aitehua_54", "length": 25.89, "rotation": -36.77, "x": 23.16, "y": -0.61 },
	{ "name": "aitehua_66", "parent": "root", "length": 36.78, "rotation": -38.76, "x": 72.96, "y": 19.75 },
	{ "name": "aitehua_64", "parent": "aitehua_61", "length": 58.83, "rotation": -71.67, "x": 28.61, "y": -34.5 },
	{ "name": "aitehua_62", "parent": "aitehua_64", "length": 61.01, "rotation": -10.94, "x": 59.16, "y": -0.67 },
	{ "name": "aitehua_67", "parent": "root", "length": 31.31, "rotation": -109.6, "x": -25.62, "y": 22.43 },
	{ "name": "aitehua_63", "parent": "aitehua_61", "length": 64.04, "rotation": -100.6, "x": -12.13, "y": -27.72 },
	{ "name": "aitehua_65", "parent": "aitehua_63", "length": 59.5, "rotation": -7.62, "x": 65.18, "y": -0.34 },
	{ "name": "bone", "parent": "aitehua_48", "length": 46.74, "rotation": -35.1, "x": 48.26, "y": -0.58 },
	{ "name": "bone2", "parent": "aitehua_52", "length": 33.32, "rotation": -45.05, "x": 42.44, "y": -0.56 },
	{ "name": "bone3", "parent": "aitehua_46", "length": 51.83, "rotation": 22.68, "x": 64.14 },
	{ "name": "bone4", "parent": "bone3", "length": 39.33, "rotation": 5.17, "x": 51.83 },
	{ "name": "bone5", "parent": "aitehua_47", "length": 42.4, "rotation": -11.84, "x": 45.77, "y": -0.16 },
	{ "name": "bone6", "parent": "bone5", "length": 32.75, "rotation": -11.93, "x": 43.27, "y": 0.02 },
	{ "name": "bone9", "parent": "root", "x": 26.69, "y": 2.46 }
],
"slots": [
	{ "name": "dizuo", "bone": "bone9", "attachment": "dizuo" },
	{ "name": "aitehua_67", "bone": "aitehua_67", "attachment": "aitehua_67" },
	{ "name": "aitehua_66", "bone": "aitehua_66", "attachment": "aitehua_66" },
	{ "name": "aitehua_65", "bone": "aitehua_65", "attachment": "aitehua_65" },
	{ "name": "aitehua_64", "bone": "aitehua_64", "attachment": "aitehua_64" },
	{ "name": "aitehua_63", "bone": "aitehua_63", "attachment": "aitehua_63" },
	{ "name": "aitehua_62", "bone": "aitehua_62", "attachment": "aitehua_62" },
	{ "name": "aitehua_61", "bone": "aitehua_61", "attachment": "aitehua_19" },
	{ "name": "aitehua_60", "bone": "aitehua_61", "attachment": "aitehua_60" },
	{ "name": "aitehua_59", "bone": "aitehua_59", "attachment": "aitehua_42" },
	{ "name": "aitehua_58", "bone": "aitehua_58", "attachment": "aitehua_58" },
	{ "name": "aitehua_52", "bone": "aitehua_52", "attachment": "aitehua_52" },
	{ "name": "aitehua_57", "bone": "aitehua_57", "attachment": "aitehua_57" },
	{ "name": "aitehua_56", "bone": "aitehua_56", "attachment": "aitehua_56" },
	{ "name": "aitehua_55", "bone": "aitehua_55", "attachment": "aitehua_55" },
	{ "name": "aitehua_54", "bone": "aitehua_54", "attachment": "aitehua_54" },
	{ "name": "aitehua_53", "bone": "aitehua_53", "attachment": "aitehua_53" },
	{ "name": "aitehua_50", "bone": "aitehua_51", "attachment": "aitehua_51" },
	{ "name": "aitehua_49", "bone": "aitehua_51", "attachment": "aitehua_49" },
	{ "name": "aitehua_48", "bone": "aitehua_48", "attachment": "aitehua_48" },
	{ "name": "aitehua_47", "bone": "aitehua_47", "attachment": "aitehua_47" },
	{ "name": "aitehua_46", "bone": "aitehua_46", "attachment": "aitehua_46" },
	{ "name": "aitehua_45", "bone": "aitehua_45", "attachment": "aitehua_45" },
	{ "name": "aitehua_44", "bone": "aitehua_44", "attachment": "aitehua_44" },
	{ "name": "aitehua_22", "bone": "aitehua_47" }
],
"ik": [
	{
		"name": "1",
		"order": 0,
		"bones": [ "aitehua_64", "aitehua_62" ],
		"target": "aitehua_66",
		"bendPositive": false
	},
	{
		"name": "2",
		"order": 1,
		"bones": [ "aitehua_63", "aitehua_65" ],
		"target": "aitehua_67",
		"bendPositive": false
	}
],
"skins": {
	"default": {
		"aitehua_22": {
			"aitehua_22": { "x": 15.72, "y": 8.42, "scaleX": 2, "scaleY": 2, "rotation": 79.35, "width": 33, "height": 50 }
		},
		"aitehua_44": {
			"aitehua_44": { "x": 14.33, "y": 0.34, "scaleX": 2, "scaleY": 2, "rotation": -116.25, "width": 29, "height": 28 }
		},
		"aitehua_45": {
			"aitehua_4": { "x": 42.38, "y": -0.34, "scaleX": 2, "scaleY": 2, "rotation": 96.7, "width": 21, "height": 52 },
			"aitehua_31": { "x": 55.01, "y": 1.56, "scaleX": 2, "scaleY": 2, "rotation": 2.58, "width": 75, "height": 29 },
			"aitehua_45": { "x": 37.08, "y": -5.57, "scaleX": 2, "scaleY": 2, "rotation": -83.69, "width": 26, "height": 59 }
		},
		"aitehua_46": {
			"aitehua_21": {
				"type": "mesh",
				"uvs": [ 0.01645, 0.29221, 0, 0.39134, 0.14167, 0.71743, 0.51732, 1, 0.62167, 1, 0.65702, 0.69921, 0.73123, 0.45917, 0.78236, 0.56541, 0.8881, 0.56376, 0.90842, 0.28896, 0.99492, 0, 0.68653, 0, 0.34805, 0.10844, 0.45642, 0.40723, 0.49227, 0.69766 ],
				"triangles": [ 5, 4, 14, 2, 14, 3, 4, 3, 14, 2, 13, 14, 2, 1, 13, 5, 14, 6, 14, 13, 6, 7, 6, 8, 8, 6, 9, 6, 13, 9, 1, 0, 13, 0, 12, 13, 13, 11, 9, 13, 12, 11, 9, 11, 10 ],
				"vertices": [ 2, 9, 62.68, -46.17, 0.67239, 24, -19.14, -42.04, 0.32761, 2, 9, 78.99, -44.08, 0.46223, 24, -3.29, -46.4, 0.53777, 2, 24, 58.12, -33.25, 0.43227, 25, 3.27, -33.68, 0.56773, 1, 25, 58.1, -3.84, 1, 1, 25, 58.95, 5.73, 1, 2, 24, 50.58, 15.97, 0.51741, 25, 0.19, 16.02, 0.48259, 2, 9, 65.76, 23.33, 0.44883, 24, 10.49, 20.9, 0.55117, 2, 9, 81.96, 35.24, 0.55837, 24, 30.03, 25.64, 0.44163, 2, 9, 77.91, 44.09, 0.56015, 24, 29.71, 35.37, 0.43985, 2, 9, 36.18, 28.96, 0.93472, 24, -14.63, 37.5, 0.06528, 1, 9, -17.48, 14.66, 1, 1, 9, -10.53, -13.19, 1, 1, 9, 19.78, -29.35, 1, 2, 9, 64.66, -1.33, 0.43575, 24, -0.03, -1.43, 0.56425, 2, 24, 51.52, 0.28, 0.57221, 25, -0.29, 0.31, 0.42779 ],
				"hull": 13
			},
			"aitehua_46": {
				"type": "mesh",
				"uvs": [ 0.66414, 0.33487, 0.5699, 0.4578, 0.50319, 0.70986, 0.29385, 0.99672, 0.18824, 0.99672, 0.00156, 0.68084, 0.00952, 0.4168, 0.01137, 0.30803, 0.39102, 0.0969, 0.72053, 0, 0.87261, 0, 0.9402, 0.17717, 1, 0.38839, 0.91485, 0.39473, 0.767, 0.32925, 0.80448, 0.12856 ],
				"triangles": [ 3, 4, 5, 2, 3, 5, 1, 2, 6, 2, 5, 6, 15, 9, 10, 9, 0, 8, 1, 8, 0, 6, 7, 8, 1, 6, 8, 9, 15, 0, 15, 10, 11, 13, 14, 15, 14, 0, 15, 11, 13, 15, 12, 13, 11 ],
				"vertices": [ 3, 8, 84.37, 12.05, 0.12956, 9, 31.64, 24.57, 0.79044, 24, -20.51, 35.2, 0.08, 2, 9, 57.21, 27.94, 0.5201, 24, 4.38, 28.45, 0.4799, 2, 24, 54.19, 26.94, 0.52146, 25, 4.77, 26.62, 0.47854, 1, 25, 61.24, 6.73, 1, 1, 25, 61.35, -3.62, 1, 2, 24, 53.07, -22.59, 0.54849, 25, -0.81, -22.61, 0.45151, 2, 9, 74.51, -25.16, 0.35434, 24, -0.13, -27.21, 0.64566, 2, 9, 54.97, -35.55, 0.92004, 24, -22.16, -29.27, 0.07996, 1, 9, 3.41, -21.2, 1, 2, 8, 149.16, 23.89, 0.03561, 9, -28.69, -1.88, 0.96439, 2, 8, 153.06, 9.5, 0.06991, 9, -35.79, 11.22, 0.93009, 2, 8, 121.28, -5.97, 0.912, 9, -8.43, 33.6, 0.088, 3, 8, 84.85, -21.92, 0.99988, 9, 23.34, 57.51, 1.1E-4, 24, -15.47, 68.8, 0, 3, 8, 77.87, -15.16, 0.99976, 9, 31.69, 52.55, 2.4E-4, 24, -9.68, 61, 0, 1, 8, 88.07, 2.61, 1, 2, 8, 126.99, 9.36, 0.88643, 9, -10.46, 17.37, 0.11357 ],
				"hull": 15
			}
		},
		"aitehua_47": {
			"aitehua_1": {
				"type": "mesh",
				"uvs": [ 0.7608, 0.12892, 0.81053, 0.25301, 0.94083, 0.41067, 1, 0.62151, 0.67246, 0.83967, 0.38153, 1, 0.09553, 1, 0.19415, 0.82317, 0.25826, 0.64901, 0.21881, 0.44367, 0.11318, 0.34986, 1.0E-5, 0.18334, 0, 0, 0.74158, 1.0E-5 ],
				"triangles": [ 11, 12, 13, 11, 13, 0, 10, 11, 0, 10, 0, 1, 9, 10, 1, 9, 1, 2, 8, 9, 2, 8, 2, 3, 4, 8, 3, 7, 8, 4, 5, 7, 4, 6, 7, 5 ],
				"vertices": [ 1, 10, 0.05, 22.66, 1, 1, 10, 19.61, 21.92, 1, 2, 26, -5.7, 24.31, 0.42827, 10, 45.18, 24.8, 0.57173, 3, 27, -21.68, 24.44, 0.02826, 26, 27.12, 28.42, 0.97093, 10, 78.14, 22.09, 8.0E-4, 2, 27, 15.78, 13.66, 0.99761, 26, 61.54, 10.12, 0.00239, 1, 27, 43.97, 2.9, 1, 1, 27, 47.73, -13.26, 1, 2, 27, 19.57, -13.94, 0.98296, 26, 59.53, -17.67, 0.01704, 2, 27, -7.74, -16.48, 0.03149, 26, 32.29, -14.51, 0.96851, 2, 26, 0.32, -17.46, 0.54234, 10, 42.5, -17.31, 0.45766, 2, 26, -14.19, -23.88, 0.0466, 10, 26.98, -20.63, 0.9534, 1, 10, 0.24, -22.27, 1, 1, 10, -27.87, -16.99, 1, 1, 10, -19.93, 25.29, 1 ],
				"hull": 14
			},
			"aitehua_26": {
				"type": "mesh",
				"uvs": [ 0.98722, 0.31455, 0.92943, 0.67266, 0.81101, 0.8725, 0.79894, 0.99231, 0.37644, 0.99231, 0.29194, 0.9219, 0.11662, 0.67803, 0.04836, 0.32436, 0.3523, 0.00769, 0.82912, 0.00769, 0.65274, 0.31804, 0.62635, 0.65463 ],
				"triangles": [ 10, 8, 9, 10, 9, 0, 7, 8, 10, 10, 6, 7, 1, 10, 0, 11, 10, 1, 11, 6, 10, 2, 11, 1, 5, 6, 11, 5, 11, 2, 4, 5, 2, 3, 4, 2 ],
				"vertices": [ 2, 26, -0.08, 19.56, 0.72252, 10, 49.7, 19, 0.27748, 2, 27, -0.38, 17.56, 0.9395, 26, 46.53, 17.28, 0.0605, 1, 27, 26.42, 17, 1, 1, 27, 41.75, 19.87, 1, 1, 27, 47.11, -3.17, 1, 1, 27, 39.27, -9.86, 1, 2, 27, 10.62, -26.61, 0.84226, 26, 48.16, -28.21, 0.15774, 3, 27, -33.29, -40.76, 0.00207, 26, 2.28, -32.98, 0.67421, 10, 41.23, -32.91, 0.32372, 1, 10, 3.92, -8.57, 1, 1, 10, 8.86, 17.67, 1, 3, 27, -41.77, -7.98, 7.4E-4, 26, 0.76, 0.84, 0.70531, 10, 46.68, 0.51, 0.29395, 3, 27, 1.18, 0.5, 0.73272, 26, 44.54, 0.27, 0.21148, 10, 89.41, -9.04, 0.0558 ],
				"hull": 10
			},
			"aitehua_47": {
				"type": "mesh",
				"uvs": [ 0, 0.26828, 0.16346, 0.13384, 0.53183, 0.00673, 0.79993, 0.00428, 0.79983, 0.15995, 0.94274, 0.38178, 0.88988, 0.72163, 0.68164, 1, 0.34397, 1, 0.482, 0.74505, 0.38337, 0.62304, 0.4019, 0.49519, 0.21166, 0.38533, 0.42292, 0.14757 ],
				"triangles": [ 8, 9, 7, 7, 9, 6, 6, 9, 11, 9, 10, 11, 6, 11, 5, 11, 4, 5, 4, 13, 2, 4, 11, 13, 4, 2, 3, 13, 1, 2, 11, 12, 13, 12, 1, 13, 0, 1, 12 ],
				"vertices": [ 1, 8, 91.55, 4.34, 1, 2, 8, 116.25, -3.53, 0.94086, 10, -13.74, -26.59, 0.05914, 2, 8, 144.41, -28.72, 0.00592, 10, -28.12, 8.35, 0.99408, 1, 10, -24.33, 30.6, 1, 1, 10, 0.54, 26.41, 1, 2, 10, 36.88, 32.47, 0.80582, 26, -15.39, 30.11, 0.19418, 3, 10, 85.09, 20.35, 4.0E-5, 26, 34.28, 28.14, 0.89983, 27, -14.61, 25.66, 0.10013, 1, 27, 40.3, 18.57, 1, 1, 27, 47, -10.19, 1, 2, 26, 45.33, -8.57, 0.33938, 27, 3.79, -7.98, 0.66062, 1, 26, 26.02, -17.53, 1, 2, 10, 45.51, -16.22, 0.45528, 26, 3.04, -15.77, 0.54472, 1, 8, 78.01, -18.19, 1, 2, 8, 119.94, -25.65, 0.40603, 10, -7.42, -5.08, 0.59397 ],
				"hull": 13
			}
		},
		"aitehua_48": {
			"aitehua_48": {
				"type": "mesh",
				"uvs": [ 0.02, 0.84953, 0.15946, 0.54678, 0.32554, 0.2116, 0.55043, 0.03125, 0.77187, 0.03125, 0.98, 0.14672, 0.98, 0.26566, 0.82031, 0.22241, 0.62309, 0.3035, 0.42588, 0.45488, 0.2598, 0.67113, 0.09026, 0.96875 ],
				"triangles": [ 7, 4, 5, 7, 5, 6, 8, 3, 4, 8, 4, 7, 2, 3, 8, 9, 2, 8, 1, 2, 9, 10, 1, 9, 0, 1, 10, 11, 0, 10 ],
				"vertices": [ 1, 11, -3.77, 5.05, 1, 2, 11, 19.99, 7.39, 0.83106, 22, -27.71, -9.74, 0.16894, 2, 11, 47.06, 9.11, 0.62422, 22, -6.55, 7.23, 0.37578, 2, 11, 70.59, -0.14, 0.39095, 22, 18.01, 13.2, 0.60905, 2, 11, 85.23, -16.75, 0.19212, 22, 39.54, 8.02, 0.80788, 2, 11, 93.44, -37.26, 0.07227, 22, 58.05, -4.03, 0.92773, 2, 11, 87.73, -42.29, 0.05124, 22, 56.27, -11.43, 0.94876, 2, 11, 79.25, -28.48, 0.1242, 22, 41.39, -5, 0.8758, 2, 11, 62.32, -17.11, 0.28444, 22, 21, -5.44, 0.71556, 2, 11, 42.01, -8.71, 0.50673, 22, -0.44, -10.25, 0.49327, 2, 11, 20.65, -5.4, 0.75345, 22, -19.82, -19.83, 0.24655, 1, 11, -4.85, -5.27, 1 ],
				"hull": 12
			}
		},
		"aitehua_49": {
			"aitehua_3": { "x": 62.75, "y": 19.44, "scaleX": 2, "scaleY": 2, "rotation": -74.84, "width": 81, "height": 77 },
			"aitehua_23": { "x": 62.3, "y": 16.09, "scaleX": 2, "scaleY": 2, "rotation": -74.84, "width": 93, "height": 79 },
			"aitehua_49": { "x": 59.65, "y": 17.01, "scaleX": 2, "scaleY": 2, "rotation": -74.84, "width": 90, "height": 83 }
		},
		"aitehua_50": {
			"aitehua_6": { "x": 35.58, "y": 0.58, "scaleX": 2, "scaleY": 2, "rotation": -74.84, "width": 52, "height": 60 },
			"aitehua_25": { "x": 40.03, "y": 0.98, "scaleX": 2, "scaleY": 2, "rotation": -74.84, "width": 56, "height": 72 },
			"aitehua_50": { "x": 38.99, "y": 4.46, "scaleX": 2, "scaleY": 2, "rotation": -74.84, "width": 68, "height": 64 },
			"aitehua_51": { "x": 38.99, "y": 4.46, "scaleX": 2, "scaleY": 2, "rotation": -74.84, "width": 68, "height": 65 }
		},
		"aitehua_52": {
			"aitehua_2": {
				"type": "mesh",
				"uvs": [ 0.99999, 0.39382, 0.89616, 0.60181, 0.57775, 0.75348, 0.37691, 0.86397, 0.38916, 1, 0.16628, 1, 0, 1, 0, 0.87698, 0.13199, 0.79464, 0.10749, 0.57148, 0, 0.30714, 0, 0, 0.66348, 0, 1, 0, 0.44549, 0.39381, 0.5753, 0.17931, 0.32612, 0.64538, 0.24672, 0.83691 ],
				"triangles": [ 15, 11, 12, 14, 10, 11, 15, 14, 11, 13, 15, 12, 0, 15, 13, 9, 10, 14, 1, 15, 0, 14, 15, 1, 16, 9, 14, 2, 14, 1, 16, 14, 2, 2, 3, 16, 8, 9, 16, 17, 8, 16, 3, 17, 16, 5, 6, 7, 5, 8, 17, 5, 7, 8, 17, 3, 4, 5, 17, 4 ],
				"vertices": [ 2, 12, -52.56, 67.59, 0, 8, 33.59, -42.12, 1, 1, 8, -1.48, -36.77, 1, 3, 23, -43.37, 17.82, 0.15354, 12, 24.42, 42.72, 0.25237, 8, -35.81, -0.55, 0.59409, 3, 23, -11.86, 26.33, 0.34277, 12, 52.7, 26.43, 0.37653, 8, -59.69, 21.69, 0.28069, 3, 23, -7.35, 47.14, 0.56188, 12, 70.61, 37.94, 0.3413, 8, -79.73, 14.51, 0.09683, 3, 23, 22.1, 38.26, 0.76112, 12, 85.13, 10.83, 0.21756, 8, -87.78, 44.19, 0.02132, 3, 23, 44.07, 31.64, 0.87916, 12, 95.97, -9.4, 0.11945, 8, -93.78, 66.34, 0.00139, 3, 23, 38.53, 13.26, 0.86918, 12, 79.05, -18.46, 0.09378, 8, -75.26, 71.36, 0.03704, 3, 23, 17.38, 6.22, 0.70272, 12, 59.13, -8.47, 0.11209, 8, -58.1, 57.14, 0.18519, 3, 23, 10.58, -28.09, 0.39545, 12, 30.04, -27.89, 0.08603, 8, -25.38, 69.51, 0.51852, 1, 8, 10.54, 94.61, 1, 1, 8, 56.79, 107.15, 1, 1, 8, 80.74, 18.78, 1, 2, 12, -106.71, 38.58, 1.0E-5, 8, 92.89, -26.05, 0.99999, 1, 8, 13.57, 31.74, 1, 1, 8, 50.56, 23.2, 1, 3, 23, -14.98, -8.34, 0.38871, 12, 25.95, 4.15, 0.19032, 8, -28.61, 37.38, 0.42096, 3, 23, 4.13, 17.1, 0.53955, 12, 57.46, 8.6, 0.2394, 8, -60.32, 40.13, 0.22106 ],
				"hull": 14
			},
			"aitehua_27": {
				"type": "mesh",
				"uvs": [ 0.98889, 0.31012, 0.98889, 0.54751, 0.58052, 0.63698, 0.47367, 0.75139, 0.5128, 0.84811, 0.31379, 0.99219, 0.01111, 0.99219, 0.01111, 0.82214, 0.01111, 0.62061, 0.13922, 0.45763, 0.2164, 0.37265, 0.33875, 0.23791, 0.45325, 0.00781, 0.98889, 0.00781 ],
				"triangles": [ 12, 13, 0, 11, 12, 0, 11, 0, 1, 10, 11, 1, 2, 10, 1, 9, 10, 2, 3, 9, 2, 8, 9, 3, 7, 8, 3, 7, 3, 4, 5, 6, 7, 4, 5, 7 ],
				"vertices": [ 1, 12, -4, 26.8, 1, 1, 12, 22.12, 42.33, 1, 2, 23, -6.27, 18, 0.56636, 12, 50.75, 16.59, 0.43364, 2, 23, 6.65, 29.83, 0.86544, 12, 68.25, 15.81, 0.13456, 2, 23, 6.27, 42.7, 0.96738, 12, 77.09, 25.16, 0.03262, 2, 23, 28.16, 56.18, 0.99861, 12, 102.1, 19.19, 0.00139, 1, 23, 54.57, 49.49, 1, 2, 23, 49.23, 28.39, 0.99451, 12, 97.31, -15.35, 0.00549, 2, 23, 42.89, 3.38, 0.90941, 12, 75.14, -28.53, 0.09059, 2, 23, 26.59, -14.01, 0.70308, 12, 51.31, -29.28, 0.29692, 2, 23, 17.19, -22.85, 0.35551, 12, 38.41, -28.87, 0.64449, 2, 23, 2.27, -36.86, 0.16008, 12, 17.96, -28.22, 0.83992, 2, 23, -14.95, -62.88, 3.0E-5, 12, -12.62, -34.41, 0.99997, 1, 12, -37.26, 7.03, 1 ],
				"hull": 14
			},
			"aitehua_52": {
				"type": "mesh",
				"uvs": [ 0.37696, 0.548, 0.27409, 0.29863, 0.43536, 0.15322, 0.58888, 0.02233, 0.81917, 0.05678, 0.97343, 0.13255, 0.96678, 0.59755, 0.8664, 0.68366, 0.74536, 0.66989, 0.74831, 0.75944, 0.64793, 0.82144, 0.57117, 0.98677, 0.37631, 0.88, 0.29069, 0.88689, 0.20802, 0.95577, 0.0486, 0.99656, 0, 0.76289, 0.05745, 0.68022, 0.06926, 0.39778, 0.16964, 0.33922, 0.29897, 0.40482, 0.33491, 0.62862, 0.54625, 0.61524 ],
				"triangles": [ 4, 2, 3, 5, 8, 4, 10, 8, 9, 7, 8, 6, 5, 6, 8, 8, 22, 4, 15, 16, 14, 11, 12, 10, 13, 14, 17, 14, 16, 17, 12, 13, 21, 13, 17, 21, 12, 22, 10, 22, 21, 0, 22, 12, 21, 10, 22, 8, 21, 18, 20, 21, 17, 18, 18, 19, 20, 0, 2, 22, 2, 0, 1, 4, 22, 2 ],
				"vertices": [ 2, 23, 12.21, -8.54, 0.87551, 12, 45.02, -15.24, 0.12449, 2, 23, 15.67, -25.43, 0.5043, 12, 35.51, -29.62, 0.4957, 2, 23, -0.69, -34.34, 0.18482, 12, 17.65, -24.34, 0.81518, 1, 8, -1.65, 53.28, 1, 1, 8, 1.02, 33.96, 1, 1, 8, -0.27, 17.87, 1, 1, 12, 21.35, 29.69, 1, 1, 12, 34.22, 25.61, 1, 2, 23, -14.88, 8.79, 0.06572, 12, 38.15, 16.18, 0.93428, 2, 23, -13.26, 15.03, 0.21625, 12, 43.71, 19.44, 0.78375, 2, 23, -3.9, 16.88, 0.60376, 12, 51.63, 14.12, 0.39624, 2, 23, 3.52, 26.04, 0.9049, 12, 63.36, 15.34, 0.0951, 1, 23, 19.64, 14.19, 1, 1, 23, 26.19, 12.73, 1, 1, 23, 34.27, 15.47, 1, 1, 23, 46.05, 15.03, 1, 1, 23, 47.64, -0.73, 1, 1, 23, 40.66, -7.17, 1, 1, 23, 33.84, -26.36, 1, 1, 23, 24.55, -27.96, 1, 1, 23, 15.51, -20.3, 1, 2, 23, 17.27, -4, 0.99839, 12, 51.81, -15.62, 0.00161, 1, 23, -0.01, 0.2, 1 ],
				"hull": 22
			}
		},
		"aitehua_53": {
			"aitehua_7": { "x": 12, "y": 0.23, "scaleX": 2, "scaleY": 2, "rotation": 82.02, "width": 17, "height": 29 },
			"aitehua_28": { "x": 12.51, "y": 1.71, "scaleX": 2, "scaleY": 2, "rotation": 54.68, "width": 25, "height": 26 },
			"aitehua_53": { "x": 12.97, "y": -1.16, "scaleX": 2, "scaleY": 2, "rotation": -108.95, "width": 23, "height": 25 }
		},
		"aitehua_54": {
			"aitehua_8": { "x": 17.26, "y": 1.61, "scaleX": 2, "scaleY": 2, "rotation": 70.12, "width": 17, "height": 32 },
			"aitehua_29": { "x": 17.76, "y": -1.84, "scaleX": 2, "scaleY": 2, "rotation": 54.59, "width": 24, "height": 36 },
			"aitehua_54": {
				"type": "mesh",
				"uvs": [ 0, 0.25738, 0.3379, 0.86216, 0.80442, 0.93195, 0.9371, 0.81099, 0.96706, 0.27599, 0.82154, 0.22017, 0.77357, 0.36772, 0.4777, 0.0316, 0.21378, 0.08525, 0.78018, 0.75537, 0.26674, 0.26565 ],
				"triangles": [ 6, 5, 4, 4, 3, 6, 10, 8, 7, 0, 8, 10, 10, 7, 6, 0, 10, 1, 10, 6, 9, 3, 9, 6, 1, 10, 9, 2, 9, 3, 1, 9, 2 ],
				"vertices": [ 3, 14, 32.94, 6.97, 0.08, 15, 3.3, 11.93, 0.92, 13, 47.7, -30.91, 0, 1, 14, 8.35, 19.48, 1, 1, 14, -17.61, 10.06, 1, 2, 14, -19.95, 1.73, 0.96, 13, 74.21, 15.15, 0.04, 2, 14, -7.33, -19.45, 0.01601, 13, 49.64, 17.2, 0.98399, 1, 13, 46.91, 9.99, 1, 2, 14, -1.64, -10.53, 0.272, 13, 53.59, 7.39, 0.728, 2, 14, 19.35, -14.98, 0.09905, 15, 5.55, -13.79, 0.90095, 2, 15, 7.38, -0.56, 0.99864, 13, 40.02, -20.25, 0.00136, 2, 14, -11.85, 4, 0.7169, 13, 71.34, 7.24, 0.2831, 3, 14, 22.93, -0.35, 0.2171, 15, -0.34, 0.07, 0.73695, 13, 47.57, -18.51, 0.04595 ],
				"hull": 9
			}
		},
		"aitehua_55": {
			"aitehua_9": { "x": 29.22, "y": -0.16, "scaleX": 2, "scaleY": 2, "rotation": 73.94, "width": 23, "height": 44 },
			"aitehua_30": { "x": 27.09, "y": 6.29, "scaleX": 2, "scaleY": 2, "rotation": 107.22, "width": 24, "height": 39 },
			"aitehua_55": { "x": 28.12, "y": 0.94, "scaleX": 2, "scaleY": 2, "rotation": 88.71, "width": 22, "height": 44 }
		},
		"aitehua_56": {
			"aitehua_11": {
				"type": "mesh",
				"uvs": [ 1, 0.55906, 1, 1, 0.47959, 1, 0, 1, 0, 0.5491, 0, 0, 0.46046, 0, 1, 0, 0.45465, 0.46784 ],
				"triangles": [ 8, 5, 6, 4, 5, 8, 8, 6, 7, 0, 8, 7, 2, 3, 4, 2, 8, 0, 2, 4, 8, 2, 0, 1 ],
				"vertices": [ 4.34, -37.18, -16.01, -31.38, -5.17, 6.66, 4.82, 41.71, 25.64, 35.77, 50.98, 28.55, 41.39, -5.11, 30.15, -44.54, 19.91, 1.47 ],
				"hull": 8
			},
			"aitehua_33": {
				"type": "mesh",
				"uvs": [ 0.86227, 0.12331, 0.93889, 0.30706, 0.96353, 0.48326, 0.96727, 0.90206, 0.86794, 0.90206, 0.82254, 0.80581, 0.41957, 0.82768, 0.27484, 0.91956, 0.01943, 0.88456, 0.03078, 0.56956, 0.08187, 0.54331, 0.01943, 0.28956, 0.27484, 0.04019, 0.59551, 0.01831, 0.50696, 0.50386 ],
				"triangles": [ 7, 8, 10, 6, 14, 5, 3, 5, 2, 3, 4, 5, 5, 14, 2, 7, 10, 6, 8, 9, 10, 14, 1, 2, 14, 13, 0, 14, 12, 13, 6, 10, 14, 10, 11, 14, 11, 12, 14, 14, 0, 1 ],
				"vertices": [ 3, 2, 24.06, -26.88, 0.21203, 3, -3.23, -26.49, 0.44785, 1, 30.8, 30.65, 0.34011, 3, 2, 13.9, -29.48, 0.19323, 3, -13.49, -28.64, 0.26223, 1, 35.21, 21.13, 0.54454, 2, 2, 5.3, -28.54, 0.09563, 1, 35.86, 12.51, 0.90437, 1, 1, 33.38, -7.44, 1, 1, 1, 26.1, -6.44, 1, 1, 1, 23.41, -1.4, 1, 1, 1, -6.28, 1.64, 1, 1, 1, -17.49, -1.26, 1, 1, 1, -35.38, 1.21, 1, 2, 2, 23.12, 38.27, 0.03557, 1, -33.08, 17.85, 0.96443, 2, 2, 23.13, 34.28, 0.83588, 3, -1.47, 34.65, 0.16412, 2, 2, 36.14, 34.83, 0.64451, 3, 11.55, 34.63, 0.35549, 2, 2, 41.54, 13.12, 0.25852, 3, 16, 12.7, 0.74148, 3, 2, 35.06, -9.73, 0.01116, 3, 8.52, -9.84, 0.95921, 1, 11.94, 38.34, 0.02962, 1, 2, 15.01, 3.83, 1 ],
				"hull": 14
			},
			"aitehua_56": {
				"type": "mesh",
				"uvs": [ 0.03891, 0.50567, 0.01069, 0.34519, 0.25108, 0.02866, 0.57245, 0, 0.81701, 0.10841, 0.99407, 0.55729, 0.91538, 0.91205, 0.80914, 0.81793, 0.81307, 0.65141, 0.63601, 0.78173, 0.43533, 0.99169, 0.1599, 0.94101, 0.01431, 0.78897, 0.47154, 0.24199 ],
				"triangles": [ 8, 4, 5, 9, 13, 8, 0, 13, 9, 11, 12, 0, 5, 7, 8, 6, 7, 5, 9, 11, 0, 10, 11, 9, 1, 2, 13, 0, 1, 13, 13, 2, 3, 13, 3, 4, 8, 13, 4 ],
				"vertices": [ 3, 3, 0.63, 38.44, 0.16036, 2, 25.06, 38.15, 0.58843, 1, -33.32, 19.78, 0.2512, 3, 3, 9.06, 38.04, 0.27235, 2, 33.5, 38.13, 0.71965, 1, -34.83, 28.08, 0.008, 2, 3, 15.21, 13.11, 0.67974, 2, 40.74, 13.49, 0.32026, 2, 3, 7.95, -11.64, 0.97257, 2, 34.57, -11.55, 0.02743, 2, 3, -6.01, -35.56, 0.75189, 2, 21.68, -36.06, 0.24811, 3, 3, -30.47, -42.98, 0.03373, 2, -2.43, -44.55, 0.12851, 1, 53.01, 7.83, 0.83775, 3, 3, -46.8, -29.86, 0, 2, -19.33, -32.16, 0.064, 1, 43.91, -11.04, 0.93599, 3, 3, -38.96, -22.37, 0, 2, -11.82, -24.34, 0.008, 1, 34.84, -5.09, 0.992, 1, 1, 36.31, 3.12, 1, 1, 1, 19.3, -1.18, 1, 1, 1, -0.39, -9.14, 1, 1, 1, -25.17, -3.27, 1, 1, 1, -37.44, 6.04, 1, 3, 3, -0.47, -0.52, 0.50286, 2, 25.67, -0.81, 0.49714, 1, 4.88, 27.49, 0 ],
				"hull": 13
			}
		},
		"aitehua_57": {
			"aitehua_10": { "x": 23.09, "y": -7.21, "scaleX": 2, "scaleY": 2, "rotation": -110.67, "width": 42, "height": 38 },
			"aitehua_34": {
				"type": "mesh",
				"uvs": [ 0.26848, 0.71811, 0.08509, 0.48667, 0.02437, 0.27793, 0.02118, 0.08683, 0.16818, 0.00451, 0.48455, 0.00294, 0.72102, 0.03979, 0.98946, 0.34555, 0.94791, 0.60426, 0.99585, 0.67482, 0.9575, 0.79536, 0.67309, 0.86886, 0.33435, 0.80124, 0.69311, 0.65287 ],
				"triangles": [ 11, 13, 10, 11, 12, 13, 10, 8, 9, 13, 0, 1, 13, 1, 5, 4, 5, 2, 8, 13, 7, 13, 5, 6, 7, 13, 6, 5, 1, 2, 2, 3, 4, 13, 8, 10, 12, 0, 13 ],
				"vertices": [ 2, 3, 7.48, 36.25, 0.92014, 2, 32, 36.27, 0.07986, 2, 3, 36.4, 42.54, 0.87591, 2, 60.62, 43.83, 0.12409, 2, 3, 56.61, 37.09, 0.97017, 2, 81.05, 39.27, 0.02983, 2, 3, 75.56, 28.34, 0.99834, 2, 100.37, 31.36, 0.00166, 1, 3, 75.55, 13.35, 1, 1, 3, 65.79, -8.06, 1, 1, 3, 55.14, -23.82, 1, 2, 3, 15.15, -39.21, 0.99969, 2, 42.98, -38.78, 3.1E-4, 2, 3, -6.2, -28, 0.84267, 2, 21.15, -28.52, 0.15733, 2, 3, -17.8, -26.35, 0.14243, 2, 9.49, -27.38, 0.85757, 1, 1, 27.89, 5.42, 1, 1, 1, 0.75, 3.95, 1, 2, 3, -2.91, 33.99, 0.12, 2, 21.72, 33.56, 0.88, 2, 3, -1.66, -3.61, 0.512, 2, 24.62, -3.95, 0.488 ],
				"hull": 13
			},
			"aitehua_57": {
				"type": "mesh",
				"uvs": [ 0.31816, 0.78473, 0.12748, 0.61223, 0, 0.29723, 0.0046, 0.15723, 0.21223, 0.01723, 0.58299, 0.01223, 0.69618, 0.01863, 0.8496, 0.16755, 0.97828, 0.38071, 0.98269, 0.69736, 0.89523, 0.89831, 0.64669, 0.98515, 0.44377, 0.96763, 0.67052, 0.70444, 0.43568, 0.12577 ],
				"triangles": [ 11, 12, 13, 10, 11, 13, 10, 13, 9, 0, 1, 13, 1, 14, 13, 13, 14, 7, 13, 8, 9, 13, 7, 8, 6, 14, 5, 14, 6, 7, 1, 2, 14, 4, 2, 3, 2, 4, 14, 14, 4, 5, 12, 0, 13 ],
				"vertices": [ 2, 2, 31.97, 41.92, 0.49858, 3, 7.7, 41.89, 0.50142, 2, 2, 57.16, 54.93, 0.13226, 3, 33.44, 53.79, 0.86774, 2, 2, 92.07, 55.13, 0.01049, 3, 68.32, 52.45, 0.98951, 2, 2, 104.51, 48.68, 0.00186, 3, 80.46, 45.46, 0.99814, 1, 3, 81.46, 17.26, 1, 1, 3, 61.55, -21.7, 1, 1, 3, 54.77, -33.23, 1, 2, 2, 61.11, -41.1, 2.1E-4, 3, 33.17, -42.33, 0.99979, 2, 2, 37.55, -44.53, 0.06278, 3, 9.48, -44.72, 0.93722, 3, 2, 16.21, -37.31, 0.26079, 3, -11.52, -36.57, 0.49921, 1, 42.49, 24.84, 0.24, 1, 1, 25.08, -0.98, 1, 1, 1, -5.87, -3.33, 1, 1, 1, -28.59, 4.44, 1, 2, 2, 25.14, -0.48, 0.8633, 3, -0.99, -0.17, 0.1367, 1, 3, 59.58, -1.03, 1 ],
				"hull": 13
			}
		},
		"aitehua_58": {
			"aitehua_5": { "x": 29.83, "y": -1.75, "scaleX": 2, "scaleY": 2, "rotation": 101.41, "width": 26, "height": 47 },
			"aitehua_32": { "x": 28.57, "y": -1.61, "scaleX": 2, "scaleY": 2, "rotation": 18.05, "width": 51, "height": 33 },
			"aitehua_58": { "x": 28.57, "y": -1.61, "scaleX": 2, "scaleY": 2, "rotation": 18.05, "width": 46, "height": 35 }
		},
		"aitehua_59": {
			"aitehua_42": { "x": 12.61, "y": -3.24, "scaleX": 2, "scaleY": 2, "rotation": -84.81, "width": 22, "height": 30 },
			"aitehua_59": { "x": 11.76, "y": -2.49, "scaleX": 2, "scaleY": 2, "rotation": -84.81, "width": 19, "height": 27 }
		},
		"aitehua_60": {
			"aitehua_12": { "x": 4.79, "y": -20.65, "scaleX": 2, "scaleY": 2, "rotation": -0.59, "width": 48, "height": 29 },
			"aitehua_35": { "x": 6.04, "y": -19.73, "scaleX": 2, "scaleY": 2, "rotation": -0.59, "width": 39, "height": 25 },
			"aitehua_60": { "x": 9.7, "y": -20.68, "scaleX": 2, "scaleY": 2, "rotation": -0.59, "width": 52, "height": 31 }
		},
		"aitehua_61": {
			"aitehua_19": { "x": 3.94, "y": -5.64, "scaleX": 2, "scaleY": 2, "rotation": -0.59, "width": 29, "height": 21 },
			"aitehua_61": { "x": 10.17, "y": -3.75, "scaleX": 2, "scaleY": 2, "rotation": -0.59, "width": 31, "height": 21 }
		},
		"aitehua_62": {
			"aitehua_15": { "x": 28.55, "y": 2.18, "scaleX": 2, "scaleY": 2, "rotation": 82.01, "width": 25, "height": 43 },
			"aitehua_41": {
				"type": "mesh",
				"uvs": [ 0.93361, 0.22205, 0.82118, 0.33486, 0.97697, 0.65074, 0.90629, 0.96755, 0.07407, 1, 0.0702, 0.2983, 0.21449, 0.03411, 0.77062, 0.03629, 0.53545, 0.22061 ],
				"triangles": [ 5, 6, 8, 1, 2, 8, 4, 5, 8, 2, 4, 8, 3, 4, 2, 1, 8, 0, 8, 7, 0, 8, 6, 7 ],
				"vertices": [ 2, 17, 60.46, 20.57, 0.776, 18, -2.03, 21.18, 0.224, 2, 17, 69.94, 14.15, 0.29253, 18, 8.33, 16.32, 0.70747, 1, 18, 34.29, 27.95, 1, 1, 18, 61.79, 27.44, 1, 1, 18, 69.98, -16.84, 1, 1, 18, 10.09, -24.31, 1, 2, 17, 42.91, -17.66, 0.22257, 18, -13.4, -19.31, 0.77743, 1, 17, 44.18, 12.35, 1, 2, 17, 59.56, -0.91, 0.44, 18, 0.44, -0.18, 0.56 ],
				"hull": 8
			},
			"aitehua_62": {
				"type": "mesh",
				"uvs": [ 0.15949, 0.58696, 0.01749, 0.59327, 0.01971, 0.6548, 0.26577, 0.87885, 0.26168, 0.98365, 0.60964, 0.96618, 0.88802, 0.95163, 0.92486, 0.79443, 1, 0.6285, 0.9658, 0.55281, 0.78567, 0.55281, 0.65877, 0.15399, 0.65058, 0.01425, 0.35583, 0, 0, 0.11032, 0.02833, 0.38396, 0.50366, 0.63541, 0.31195, 0.17085 ],
				"triangles": [ 4, 3, 5, 6, 5, 7, 3, 16, 5, 10, 7, 5, 10, 5, 16, 2, 0, 3, 3, 0, 16, 8, 10, 9, 8, 7, 10, 2, 1, 0, 0, 17, 16, 16, 11, 10, 16, 17, 11, 0, 15, 17, 15, 14, 17, 11, 13, 12, 11, 17, 13, 17, 14, 13 ],
				"vertices": [ 1, 18, 35.51, -15.3, 1, 1, 18, 34.81, -24.38, 1, 1, 18, 40.31, -25.01, 1, 2, 18, 62.47, -12.22, 0.96372, 16, -7.11, -10.04, 0.03628, 2, 18, 71.77, -13.79, 0.27554, 16, -1.26, -17.44, 0.72446, 1, 16, 14.81, -1.95, 1, 2, 18, 74.49, 26.31, 0.04948, 16, 27.64, 10.49, 0.95052, 2, 18, 60.81, 30.61, 0.95695, 16, 20.37, 22.85, 0.04305, 1, 18, 46.69, 37.45, 1, 2, 17, 103.96, 28.92, 2.0E-5, 18, 39.64, 36.23, 0.99998, 2, 17, 100.6, 17.9, 0.01048, 18, 38.03, 24.81, 0.98952, 2, 17, 63.9, 20.6, 0.51047, 18, 1.36, 21.76, 0.48953, 2, 17, 51.72, 23.77, 0.84, 18, -11.17, 22.99, 0.16, 2, 17, 44.98, 6.11, 0.99956, 18, -15.06, 4.48, 4.4E-4, 2, 17, 47.83, -18.57, 0.448, 18, -8.39, -19.45, 0.552, 2, 17, 71.92, -24.03, 0.048, 18, 16.25, -21.08, 0.952, 2, 17, 102.44, -1.54, 8.0E-5, 18, 42.89, 5.9, 0.99992, 2, 17, 58.87, -1.07, 0.48979, 18, -0.22, -0.44, 0.51021 ],
				"hull": 16
			}
		},
		"aitehua_63": {
			"aitehua_13": { "x": 37.92, "y": 5.79, "scaleX": 2, "scaleY": 2, "rotation": 100.01, "width": 26, "height": 37 },
			"aitehua_36": {
				"type": "mesh",
				"uvs": [ 0.97339, 0.2657, 0.67275, 0.86774, 0.48172, 0.98973, 0.02035, 0.93529, 0.03152, 0.74285, 0.04584, 0.24693, 0.06061, 0, 0.93939, 0, 0.3452, 0.80394, 0.48107, 0.07046 ],
				"triangles": [ 2, 8, 1, 0, 1, 9, 4, 5, 8, 1, 8, 9, 8, 5, 9, 9, 7, 0, 5, 6, 9, 9, 6, 7, 3, 4, 8, 3, 8, 2 ],
				"vertices": [ 1, 20, 16.15, 36.58, 1, 2, 21, 0.75, 19.31, 0.11092, 20, 69.73, 18.44, 0.88908, 2, 21, 14.09, 9.49, 0.73064, 20, 80.86, 6.18, 0.26936, 2, 21, 16.39, -21.25, 0.36733, 20, 77.05, -24.41, 0.63267, 2, 21, -0.26, -24.41, 0.12498, 20, 60.1, -24.21, 0.87502, 1, 20, 16.45, -24.66, 1, 1, 20, -5.3, -24.38, 1, 1, 20, -7.15, 33.59, 1, 2, 21, 0.23, -3.02, 0.608, 20, 64.81, -3.35, 0.392, 1, 20, 0.01, 3.56, 1 ],
				"hull": 8
			},
			"aitehua_63": { "x": 36.41, "y": 2.37, "scaleX": 2, "scaleY": 2, "rotation": 100.01, "width": 32, "height": 48 }
		},
		"aitehua_64": {
			"aitehua_18": { "x": 29.93, "y": -0.87, "scaleX": 2, "scaleY": 2, "rotation": 71.08, "width": 24, "height": 39 },
			"aitehua_40": { "x": 30.94, "y": 3.1, "scaleX": 2, "scaleY": 2, "rotation": 89.41, "width": 25, "height": 37 },
			"aitehua_64": { "x": 26.6, "y": -3.92, "scaleX": 2, "scaleY": 2, "rotation": 71.08, "width": 36, "height": 41 }
		},
		"aitehua_65": {
			"aitehua_14": { "x": 32.8, "y": -4.31, "scaleX": 2, "scaleY": 2, "rotation": 107.63, "width": 28, "height": 44 },
			"aitehua_37": { "x": 30.45, "y": -5.27, "scaleX": 2, "scaleY": 2, "rotation": 103.68, "width": 30, "height": 40 },
			"aitehua_65": { "x": 32.56, "y": -5.46, "scaleX": 2, "scaleY": 2, "rotation": 107.63, "width": 28, "height": 40 }
		},
		"aitehua_66": {
			"aitehua_16": { "x": 7.94, "y": -3.68, "scaleX": 2, "scaleY": 2, "rotation": 38.76, "width": 25, "height": 25 },
			"aitehua_39": { "x": 13.9, "y": 2.26, "scaleX": 2, "scaleY": 2, "rotation": 35.88, "width": 25, "height": 20 },
			"aitehua_66": { "x": 12.78, "y": -0.3, "scaleX": 2, "scaleY": 2, "rotation": 38.76, "width": 26, "height": 20 }
		},
		"aitehua_67": {
			"aitehua_17": { "x": 11.29, "y": 1.8, "scaleX": 2, "scaleY": 2, "rotation": 109.6, "width": 26, "height": 20 },
			"aitehua_38": { "x": 10.41, "y": 5.65, "scaleX": 2, "scaleY": 2, "rotation": 108.5, "width": 28, "height": 21 },
			"aitehua_40": { "path": "aitehua_39", "x": 2.57, "y": 13.07, "scaleX": 2, "scaleY": 2, "rotation": 106.73, "width": 25, "height": 20 },
			"aitehua_67": { "x": 11.49, "y": 0.18, "scaleX": 2, "scaleY": 2, "rotation": 109.6, "width": 22, "height": 19 }
		},
		"dizuo": {
			"dizuo": { "width": 175, "height": 60 }
		}
	}
},
"animations": {
	"holdon": {
		"slots": {
			"aitehua_50": {
				"attachment": [
					{ "time": 1.2667, "name": "aitehua_50" },
					{ "time": 1.3667, "name": "aitehua_51" }
				]
			},
			"aitehua_62": {
				"attachment": [
					{ "time": 0, "name": "aitehua_62" },
					{ "time": 1.3333, "name": "aitehua_62" }
				]
			},
			"aitehua_66": {
				"attachment": [
					{ "time": 0, "name": "aitehua_66" },
					{ "time": 1.3333, "name": "aitehua_66" }
				]
			}
		},
		"bones": {
			"aitehua_61": {
				"rotate": [
					{ "time": 0, "angle": 0, "curve": "stepped" },
					{ "time": 1.3333, "angle": 0, "curve": "stepped" },
					{ "time": 2.6667, "angle": 0 }
				],
				"translate": [
					{
						"time": 0,
						"x": 0,
						"y": 0,
						"curve": [ 0.25, 0, 0.75, 1 ]
					},
					{
						"time": 0.6667,
						"x": 0,
						"y": -2,
						"curve": [ 0.25, 0, 0.75, 1 ]
					},
					{
						"time": 1.3333,
						"x": 0,
						"y": 0,
						"curve": [ 0.25, 0, 0.75, 1 ]
					},
					{
						"time": 2,
						"x": 0,
						"y": -2,
						"curve": [ 0.25, 0, 0.75, 1 ]
					},
					{ "time": 2.6667, "x": 0, "y": 0 }
				],
				"scale": [
					{ "time": 0, "x": 1, "y": 1, "curve": "stepped" },
					{ "time": 1.3333, "x": 1, "y": 1, "curve": "stepped" },
					{ "time": 2.6667, "x": 1, "y": 1 }
				]
			},
			"aitehua_56": {
				"rotate": [
					{
						"time": 0,
						"angle": 0,
						"curve": [ 0.25, 0, 0.75, 1 ]
					},
					{
						"time": 0.6667,
						"angle": -0.68,
						"curve": [ 0.25, 0, 0.75, 1 ]
					},
					{
						"time": 1.3333,
						"angle": 0,
						"curve": [ 0.25, 0, 0.75, 1 ]
					},
					{
						"time": 2,
						"angle": -0.68,
						"curve": [ 0.25, 0, 0.75, 1 ]
					},
					{ "time": 2.6667, "angle": 0 }
				],
				"translate": [
					{ "time": 0, "x": 0, "y": 0, "curve": "stepped" },
					{ "time": 1.3333, "x": 0, "y": 0, "curve": "stepped" },
					{ "time": 2.6667, "x": 0, "y": 0 }
				],
				"scale": [
					{ "time": 0, "x": 1, "y": 1, "curve": "stepped" },
					{ "time": 1.3333, "x": 1, "y": 1, "curve": "stepped" },
					{ "time": 2.6667, "x": 1, "y": 1 }
				]
			},
			"aitehua_57": {
				"rotate": [
					{
						"time": 0,
						"angle": -0.41,
						"curve": [ 0.379, 0.6, 0.724, 1 ]
					},
					{
						"time": 0.1667,
						"angle": 0,
						"curve": [ 0.25, 0, 0.75, 1 ]
					},
					{
						"time": 0.8333,
						"angle": -2.24,
						"curve": [ 0.242, 0, 0.667, 0.67 ]
					},
					{
						"time": 1.3333,
						"angle": -0.41,
						"curve": [ 0.379, 0.6, 0.724, 1 ]
					},
					{
						"time": 1.5,
						"angle": 0,
						"curve": [ 0.25, 0, 0.75, 1 ]
					},
					{
						"time": 2.1667,
						"angle": -2.24,
						"curve": [ 0.242, 0, 0.667, 0.67 ]
					},
					{ "time": 2.6667, "angle": -0.41 }
				],
				"translate": [
					{
						"time": 0,
						"x": 0,
						"y": 0,
						"curve": [ 0.25, 0, 0.75, 1 ]
					},
					{
						"time": 0.6667,
						"x": -4.04,
						"y": 1.29,
						"curve": [ 0.25, 0, 0.75, 1 ]
					},
					{
						"time": 1.3333,
						"x": 0,
						"y": 0,
						"curve": [ 0.25, 0, 0.75, 1 ]
					},
					{
						"time": 2,
						"x": -4.04,
						"y": 1.29,
						"curve": [ 0.25, 0, 0.75, 1 ]
					},
					{ "time": 2.6667, "x": 0, "y": 0 }
				],
				"scale": [
					{ "time": 0, "x": 1, "y": 1, "curve": "stepped" },
					{ "time": 1.3333, "x": 1, "y": 1, "curve": "stepped" },
					{ "time": 2.6667, "x": 1, "y": 1 }
				]
			},
			"aitehua_59": {
				"rotate": [
					{ "time": 0, "angle": 0, "curve": "stepped" },
					{ "time": 1.3333, "angle": 0, "curve": "stepped" },
					{ "time": 2.6667, "angle": 0 }
				],
				"translate": [
					{ "time": 0, "x": 0, "y": 0, "curve": "stepped" },
					{ "time": 1.3333, "x": 0, "y": 0, "curve": "stepped" },
					{ "time": 2.6667, "x": 0, "y": 0 }
				],
				"scale": [
					{ "time": 0, "x": 1, "y": 1, "curve": "stepped" },
					{ "time": 1.3333, "x": 1, "y": 1, "curve": "stepped" },
					{ "time": 2.6667, "x": 1, "y": 1 }
				]
			},
			"aitehua_51": {
				"rotate": [
					{
						"time": 0,
						"angle": -3.18,
						"curve": [ 0.333, 0.33, 0.758, 1 ]
					},
					{
						"time": 0.5,
						"angle": 0,
						"curve": [ 0.25, 0, 0.75, 1 ]
					},
					{
						"time": 1.1667,
						"angle": -3.9,
						"curve": [ 0.25, 0, 1, 0.99 ]
					},
					{
						"time": 1.3333,
						"angle": -3.18,
						"curve": [ 0.333, 0.33, 0.758, 1 ]
					},
					{
						"time": 1.8333,
						"angle": 0,
						"curve": [ 0.25, 0, 0.75, 1 ]
					},
					{
						"time": 2.5,
						"angle": -3.9,
						"curve": [ 0.25, 0, 1, 0.99 ]
					},
					{ "time": 2.6667, "angle": -3.18 }
				],
				"translate": [
					{ "time": 0, "x": 0, "y": 0, "curve": "stepped" },
					{ "time": 1.3333, "x": 0, "y": 0, "curve": "stepped" },
					{ "time": 2.6667, "x": 0, "y": 0 }
				],
				"scale": [
					{ "time": 0, "x": 1, "y": 1, "curve": "stepped" },
					{ "time": 1.3333, "x": 1, "y": 1, "curve": "stepped" },
					{ "time": 2.6667, "x": 1, "y": 1 }
				]
			},
			"aitehua_48": {
				"rotate": [
					{
						"time": 0,
						"angle": 0.09,
						"curve": [ 0.375, 0.5, 0.75, 1 ]
					},
					{
						"time": 0.3333,
						"angle": -2.43,
						"curve": [ 0.25, 0, 0.75, 1 ]
					},
					{
						"time": 1,
						"angle": 2.61,
						"curve": [ 0.25, 0, 0.625, 0.5 ]
					},
					{
						"time": 1.3333,
						"angle": 0.09,
						"curve": [ 0.375, 0.5, 0.75, 1 ]
					},
					{
						"time": 1.6667,
						"angle": -2.43,
						"curve": [ 0.25, 0, 0.75, 1 ]
					},
					{
						"time": 2.3333,
						"angle": 2.61,
						"curve": [ 0.25, 0, 0.625, 0.5 ]
					},
					{ "time": 2.6667, "angle": 0.09 }
				],
				"translate": [
					{ "time": 0, "x": 0, "y": 0, "curve": "stepped" },
					{ "time": 1.3333, "x": 0, "y": 0, "curve": "stepped" },
					{ "time": 2.6667, "x": 0, "y": 0 }
				],
				"scale": [
					{ "time": 0, "x": 1, "y": 1, "curve": "stepped" },
					{ "time": 1.3333, "x": 1, "y": 1, "curve": "stepped" },
					{ "time": 2.6667, "x": 1, "y": 1 }
				]
			},
			"bone": {
				"rotate": [
					{
						"time": 0,
						"angle": 8.92,
						"curve": [ 0.333, 0.33, 0.758, 1 ]
					},
					{
						"time": 0.5,
						"angle": -8.93,
						"curve": [ 0.25, 0, 0.75, 1 ]
					},
					{
						"time": 1.1667,
						"angle": 12.96,
						"curve": [ 0.276, 0, 0.621, 0.4 ]
					},
					{
						"time": 1.3333,
						"angle": 8.92,
						"curve": [ 0.333, 0.33, 0.758, 1 ]
					},
					{
						"time": 1.8333,
						"angle": -8.93,
						"curve": [ 0.25, 0, 0.75, 1 ]
					},
					{
						"time": 2.5,
						"angle": 12.96,
						"curve": [ 0.276, 0, 0.621, 0.4 ]
					},
					{ "time": 2.6667, "angle": 8.92 }
				],
				"translate": [
					{ "time": 0, "x": 0, "y": 0, "curve": "stepped" },
					{ "time": 1.3333, "x": 0, "y": 0, "curve": "stepped" },
					{ "time": 2.6667, "x": 0, "y": 0 }
				],
				"scale": [
					{ "time": 0, "x": 1, "y": 1, "curve": "stepped" },
					{ "time": 1.3333, "x": 1, "y": 1, "curve": "stepped" },
					{ "time": 2.6667, "x": 1, "y": 1 }
				]
			},
			"aitehua_52": {
				"rotate": [
					{
						"time": 0,
						"angle": -4.44,
						"curve": [ 0, 0, 0.75, 1 ]
					},
					{
						"time": 0.5,
						"angle": 2.97,
						"curve": [ 0.25, 0, 0.75, 1 ]
					},
					{
						"time": 1.1667,
						"angle": -5.43,
						"curve": [ 0.299, 0, 0.636, 0.36 ]
					},
					{
						"time": 1.3333,
						"angle": -4.44,
						"curve": [ 0, 0, 0.75, 1 ]
					},
					{
						"time": 1.8333,
						"angle": 2.97,
						"curve": [ 0.25, 0, 0.75, 1 ]
					},
					{
						"time": 2.5,
						"angle": -5.43,
						"curve": [ 0.299, 0, 0.636, 0.36 ]
					},
					{ "time": 2.6667, "angle": -4.44 }
				],
				"translate": [
					{ "time": 0, "x": 0, "y": 0, "curve": "stepped" },
					{ "time": 1.3333, "x": 0, "y": 0, "curve": "stepped" },
					{ "time": 2.6667, "x": 0, "y": 0 }
				],
				"scale": [
					{ "time": 0, "x": 1, "y": 1, "curve": "stepped" },
					{ "time": 1.3333, "x": 1, "y": 1, "curve": "stepped" },
					{ "time": 2.6667, "x": 1, "y": 1 }
				]
			},
			"bone2": {
				"rotate": [
					{
						"time": 0,
						"angle": -2.72,
						"curve": [ 0, 0, 0.75, 1 ]
					},
					{
						"time": 0.1667,
						"angle": -10.62,
						"curve": [ 0.25, 0, 0.75, 1 ]
					},
					{
						"time": 0.8333,
						"angle": 13.38,
						"curve": [ 0.26, 0, 0.618, 0.44 ]
					},
					{
						"time": 1.3333,
						"angle": -2.72,
						"curve": [ 0, 0, 0.75, 1 ]
					},
					{
						"time": 1.5,
						"angle": -10.62,
						"curve": [ 0.25, 0, 0.75, 1 ]
					},
					{
						"time": 2.1667,
						"angle": 13.38,
						"curve": [ 0.26, 0, 0.618, 0.44 ]
					},
					{ "time": 2.6667, "angle": -2.72 }
				],
				"translate": [
					{ "time": 0, "x": 0, "y": 0, "curve": "stepped" },
					{ "time": 1.3333, "x": 0, "y": 0, "curve": "stepped" },
					{ "time": 2.6667, "x": 0, "y": 0 }
				],
				"scale": [
					{ "time": 0, "x": 1, "y": 1, "curve": "stepped" },
					{ "time": 1.3333, "x": 1, "y": 1, "curve": "stepped" },
					{ "time": 2.6667, "x": 1, "y": 1 }
				]
			},
			"aitehua_46": {
				"rotate": [
					{
						"time": 0,
						"angle": -0.65,
						"curve": [ 0.333, 0.33, 0.758, 1 ]
					},
					{
						"time": 0.5,
						"angle": 3.34,
						"curve": [ 0.25, 0, 0.75, 1 ]
					},
					{
						"time": 1.1667,
						"angle": -1.55,
						"curve": [ 0.276, 0, 0.621, 0.4 ]
					},
					{
						"time": 1.3333,
						"angle": -0.65,
						"curve": [ 0.333, 0.33, 0.758, 1 ]
					},
					{
						"time": 1.8333,
						"angle": 3.34,
						"curve": [ 0.25, 0, 0.75, 1 ]
					},
					{
						"time": 2.5,
						"angle": -1.55,
						"curve": [ 0.276, 0, 0.621, 0.4 ]
					},
					{ "time": 2.6667, "angle": -0.65 }
				],
				"translate": [
					{ "time": 0, "x": 0, "y": 0, "curve": "stepped" },
					{ "time": 1.3333, "x": 0, "y": 0, "curve": "stepped" },
					{ "time": 2.6667, "x": 0, "y": 0 }
				],
				"scale": [
					{ "time": 0, "x": 1, "y": 1, "curve": "stepped" },
					{ "time": 1.3333, "x": 1, "y": 1, "curve": "stepped" },
					{ "time": 2.6667, "x": 1, "y": 1 }
				]
			},
			"bone3": {
				"rotate": [
					{
						"time": 0,
						"angle": -4,
						"curve": [ 0.25, 0, 0.75, 1 ]
					},
					{
						"time": 0.6667,
						"angle": 3.84,
						"curve": [ 0.25, 0, 0.75, 1 ]
					},
					{
						"time": 1.3333,
						"angle": -4,
						"curve": [ 0.25, 0, 0.75, 1 ]
					},
					{
						"time": 2,
						"angle": 3.84,
						"curve": [ 0.25, 0, 0.75, 1 ]
					},
					{ "time": 2.6667, "angle": -4 }
				],
				"translate": [
					{ "time": 0, "x": 0, "y": 0, "curve": "stepped" },
					{ "time": 1.3333, "x": 0, "y": 0, "curve": "stepped" },
					{ "time": 2.6667, "x": 0, "y": 0 }
				],
				"scale": [
					{ "time": 0, "x": 1, "y": 1, "curve": "stepped" },
					{ "time": 1.3333, "x": 1, "y": 1, "curve": "stepped" },
					{ "time": 2.6667, "x": 1, "y": 1 }
				]
			},
			"bone4": {
				"rotate": [
					{
						"time": 0,
						"angle": -1.7,
						"curve": [ 0.329, 0.32, 0.664, 0.66 ]
					},
					{
						"time": 0.1667,
						"angle": -6.44,
						"curve": [ 0.25, 0, 0.75, 1 ]
					},
					{
						"time": 0.8333,
						"angle": 7.97,
						"curve": [ 0.26, 0, 0.618, 0.44 ]
					},
					{
						"time": 1.3333,
						"angle": -1.7,
						"curve": [ 0.329, 0.32, 0.664, 0.66 ]
					},
					{
						"time": 1.5,
						"angle": -6.44,
						"curve": [ 0.25, 0, 0.75, 1 ]
					},
					{
						"time": 2.1667,
						"angle": 7.97,
						"curve": [ 0.26, 0, 0.618, 0.44 ]
					},
					{ "time": 2.6667, "angle": -1.7 }
				],
				"translate": [
					{ "time": 0, "x": 0, "y": 0, "curve": "stepped" },
					{ "time": 1.3333, "x": 0, "y": 0, "curve": "stepped" },
					{ "time": 2.6667, "x": 0, "y": 0 }
				],
				"scale": [
					{ "time": 0, "x": 1, "y": 1, "curve": "stepped" },
					{ "time": 1.3333, "x": 1, "y": 1, "curve": "stepped" },
					{ "time": 2.6667, "x": 1, "y": 1 }
				]
			},
			"aitehua_47": {
				"rotate": [
					{
						"time": 0,
						"angle": 2.86,
						"curve": [ 0.25, 0, 0.75, 1 ]
					},
					{
						"time": 0.6667,
						"angle": -1.19,
						"curve": [ 0.25, 0, 0.75, 1 ]
					},
					{
						"time": 1.3333,
						"angle": 2.86,
						"curve": [ 0.25, 0, 0.75, 1 ]
					},
					{
						"time": 2,
						"angle": -1.19,
						"curve": [ 0.25, 0, 0.75, 1 ]
					},
					{ "time": 2.6667, "angle": 2.86 }
				],
				"translate": [
					{ "time": 0, "x": 0, "y": 0, "curve": "stepped" },
					{ "time": 1.3333, "x": 0, "y": 0, "curve": "stepped" },
					{ "time": 2.6667, "x": 0, "y": 0 }
				],
				"scale": [
					{ "time": 0, "x": 1, "y": 1, "curve": "stepped" },
					{ "time": 1.3333, "x": 1, "y": 1, "curve": "stepped" },
					{ "time": 2.6667, "x": 1, "y": 1 }
				]
			},
			"bone5": {
				"rotate": [
					{
						"time": 0,
						"angle": 5.94,
						"curve": [ 0.379, 0.6, 0.724, 1 ]
					},
					{
						"time": 0.1667,
						"angle": 8.12,
						"curve": [ 0.25, 0, 0.75, 1 ]
					},
					{
						"time": 0.8333,
						"angle": -3.73,
						"curve": [ 0.25, 0, 0.625, 0.5 ]
					},
					{
						"time": 1.3333,
						"angle": 5.94,
						"curve": [ 0.379, 0.6, 0.724, 1 ]
					},
					{
						"time": 1.5,
						"angle": 8.12,
						"curve": [ 0.25, 0, 0.75, 1 ]
					},
					{
						"time": 2.1667,
						"angle": -3.73,
						"curve": [ 0.25, 0, 0.625, 0.5 ]
					},
					{ "time": 2.6667, "angle": 5.94 }
				],
				"translate": [
					{ "time": 0, "x": 0, "y": 0, "curve": "stepped" },
					{ "time": 1.3333, "x": 0, "y": 0, "curve": "stepped" },
					{ "time": 2.6667, "x": 0, "y": 0 }
				],
				"scale": [
					{ "time": 0, "x": 1, "y": 1, "curve": "stepped" },
					{ "time": 1.3333, "x": 1, "y": 1, "curve": "stepped" },
					{ "time": 2.6667, "x": 1, "y": 1 }
				]
			},
			"bone6": {
				"rotate": [
					{
						"time": 0,
						"angle": 0.45,
						"curve": [ 0.375, 0.5, 0.75, 1 ]
					},
					{
						"time": 0.3333,
						"angle": 10.16,
						"curve": [ 0.25, 0, 0.75, 1 ]
					},
					{
						"time": 1,
						"angle": -9.26,
						"curve": [ 0.25, 0, 0.625, 0.5 ]
					},
					{
						"time": 1.3333,
						"angle": 0.45,
						"curve": [ 0.375, 0.5, 0.75, 1 ]
					},
					{
						"time": 1.6667,
						"angle": 10.16,
						"curve": [ 0.25, 0, 0.75, 1 ]
					},
					{
						"time": 2.3333,
						"angle": -9.26,
						"curve": [ 0.25, 0, 0.625, 0.5 ]
					},
					{ "time": 2.6667, "angle": 0.45 }
				],
				"translate": [
					{ "time": 0, "x": 0, "y": 0, "curve": "stepped" },
					{ "time": 1.3333, "x": 0, "y": 0, "curve": "stepped" },
					{ "time": 2.6667, "x": 0, "y": 0 }
				],
				"scale": [
					{ "time": 0, "x": 1, "y": 1, "curve": "stepped" },
					{ "time": 1.3333, "x": 1, "y": 1, "curve": "stepped" },
					{ "time": 2.6667, "x": 1, "y": 1 }
				]
			},
			"aitehua_55": {
				"rotate": [
					{
						"time": 0,
						"angle": -3.5,
						"curve": [ 0.379, 0.6, 0.724, 1 ]
					},
					{
						"time": 0.1667,
						"angle": -4.04,
						"curve": [ 0.25, 0, 0.75, 1 ]
					},
					{
						"time": 0.8333,
						"angle": 2.93,
						"curve": [ 0.242, 0, 0.667, 0.67 ]
					},
					{
						"time": 1.3333,
						"angle": -3.5,
						"curve": [ 0.379, 0.6, 0.724, 1 ]
					},
					{
						"time": 1.5,
						"angle": -4.04,
						"curve": [ 0.25, 0, 0.75, 1 ]
					},
					{
						"time": 2.1667,
						"angle": 2.93,
						"curve": [ 0.242, 0, 0.667, 0.67 ]
					},
					{ "time": 2.6667, "angle": -3.5 }
				],
				"translate": [
					{ "time": 0, "x": 0, "y": 0, "curve": "stepped" },
					{ "time": 1.3333, "x": 0, "y": 0, "curve": "stepped" },
					{ "time": 2.6667, "x": 0, "y": 0 }
				],
				"scale": [
					{ "time": 0, "x": 1, "y": 1, "curve": "stepped" },
					{ "time": 1.3333, "x": 1, "y": 1, "curve": "stepped" },
					{ "time": 2.6667, "x": 1, "y": 1 }
				]
			},
			"aitehua_54": {
				"rotate": [
					{
						"time": 0,
						"angle": -0.98,
						"curve": [ 0.379, 0.6, 0.724, 1 ]
					},
					{
						"time": 0.1667,
						"angle": 0,
						"curve": [ 0.25, 0, 0.75, 1 ]
					},
					{
						"time": 0.8333,
						"angle": -365.29,
						"curve": [ 0.242, 0, 0.667, 0.67 ]
					},
					{
						"time": 1.3333,
						"angle": -0.98,
						"curve": [ 0.379, 0.6, 0.724, 1 ]
					},
					{
						"time": 1.5,
						"angle": 0,
						"curve": [ 0.25, 0, 0.75, 1 ]
					},
					{
						"time": 2.1667,
						"angle": -365.29,
						"curve": [ 0.242, 0, 0.667, 0.67 ]
					},
					{ "time": 2.6667, "angle": -0.98 }
				],
				"translate": [
					{ "time": 0, "x": 0, "y": 0, "curve": "stepped" },
					{ "time": 1.3333, "x": 0, "y": 0, "curve": "stepped" },
					{ "time": 2.6667, "x": 0, "y": 0 }
				],
				"scale": [
					{ "time": 0, "x": 1, "y": 1, "curve": "stepped" },
					{ "time": 1.3333, "x": 1, "y": 1, "curve": "stepped" },
					{ "time": 2.6667, "x": 1, "y": 1 }
				]
			},
			"aitehua_53": {
				"rotate": [
					{
						"time": 0,
						"angle": -0.42,
						"curve": [ 0.351, 0.65, 0.686, 1 ]
					},
					{
						"time": 0.1667,
						"angle": 0,
						"curve": [ 0.25, 0, 0.75, 1 ]
					},
					{
						"time": 0.8333,
						"angle": -4.53,
						"curve": [ 0.25, 0, 1, 0.97 ]
					},
					{
						"time": 1.3333,
						"angle": -0.42,
						"curve": [ 0.351, 0.65, 0.686, 1 ]
					},
					{
						"time": 1.5,
						"angle": 0,
						"curve": [ 0.25, 0, 0.75, 1 ]
					},
					{
						"time": 2.1667,
						"angle": -4.53,
						"curve": [ 0.25, 0, 1, 0.97 ]
					},
					{ "time": 2.6667, "angle": -0.42 }
				],
				"translate": [
					{ "time": 0, "x": 0, "y": 0, "curve": "stepped" },
					{ "time": 1.3333, "x": 0, "y": 0, "curve": "stepped" },
					{ "time": 2.6667, "x": 0, "y": 0 }
				],
				"scale": [
					{ "time": 0, "x": 1, "y": 1, "curve": "stepped" },
					{ "time": 1.3333, "x": 1, "y": 1, "curve": "stepped" },
					{ "time": 2.6667, "x": 1, "y": 1 }
				]
			},
			"aitehua_58": {
				"rotate": [
					{
						"time": 0,
						"angle": -1.51,
						"curve": [ 0.379, 0.6, 0.724, 1 ]
					},
					{
						"time": 0.1667,
						"angle": 0,
						"curve": [ 0.25, 0, 0.75, 1 ]
					},
					{
						"time": 0.8333,
						"angle": -8.21,
						"curve": [ 0.242, 0, 0.667, 0.67 ]
					},
					{
						"time": 1.3333,
						"angle": -1.51,
						"curve": [ 0.379, 0.6, 0.724, 1 ]
					},
					{
						"time": 1.5,
						"angle": 0,
						"curve": [ 0.25, 0, 0.75, 1 ]
					},
					{
						"time": 2.1667,
						"angle": -8.21,
						"curve": [ 0.242, 0, 0.667, 0.67 ]
					},
					{ "time": 2.6667, "angle": -1.51 }
				],
				"translate": [
					{ "time": 0, "x": 0, "y": 0, "curve": "stepped" },
					{ "time": 1.3333, "x": 0, "y": 0, "curve": "stepped" },
					{ "time": 2.6667, "x": 0, "y": 0 }
				],
				"scale": [
					{ "time": 0, "x": 1, "y": 1, "curve": "stepped" },
					{ "time": 1.3333, "x": 1, "y": 1, "curve": "stepped" },
					{ "time": 2.6667, "x": 1, "y": 1 }
				]
			},
			"aitehua_45": {
				"rotate": [
					{
						"time": 0,
						"angle": 1.73,
						"curve": [ 0.379, 0.6, 0.724, 1 ]
					},
					{
						"time": 0.1667,
						"angle": 0,
						"curve": [ 0.25, 0, 0.75, 1 ]
					},
					{
						"time": 0.8333,
						"angle": 9.37,
						"curve": [ 0.242, 0, 0.667, 0.67 ]
					},
					{
						"time": 1.3333,
						"angle": 1.73,
						"curve": [ 0.379, 0.6, 0.724, 1 ]
					},
					{
						"time": 1.5,
						"angle": 0,
						"curve": [ 0.25, 0, 0.75, 1 ]
					},
					{
						"time": 2.1667,
						"angle": 9.37,
						"curve": [ 0.242, 0, 0.667, 0.67 ]
					},
					{ "time": 2.6667, "angle": 1.73 }
				],
				"translate": [
					{ "time": 0, "x": 0, "y": 0, "curve": "stepped" },
					{ "time": 1.3333, "x": 0, "y": 0, "curve": "stepped" },
					{ "time": 2.6667, "x": 0, "y": 0 }
				],
				"scale": [
					{ "time": 0, "x": 1, "y": 1, "curve": "stepped" },
					{ "time": 1.3333, "x": 1, "y": 1, "curve": "stepped" },
					{ "time": 2.6667, "x": 1, "y": 1 }
				]
			},
			"aitehua_44": {
				"rotate": [
					{
						"time": 0,
						"angle": 0.62,
						"curve": [ 0.379, 0.6, 0.724, 1 ]
					},
					{
						"time": 0.1667,
						"angle": 0,
						"curve": [ 0.25, 0, 0.75, 1 ]
					},
					{
						"time": 0.8333,
						"angle": 3.37,
						"curve": [ 0.242, 0, 0.667, 0.67 ]
					},
					{
						"time": 1.3333,
						"angle": 0.62,
						"curve": [ 0.379, 0.6, 0.724, 1 ]
					},
					{
						"time": 1.5,
						"angle": 0,
						"curve": [ 0.25, 0, 0.75, 1 ]
					},
					{
						"time": 2.1667,
						"angle": 3.37,
						"curve": [ 0.242, 0, 0.667, 0.67 ]
					},
					{ "time": 2.6667, "angle": 0.62 }
				],
				"translate": [
					{ "time": 0, "x": 0, "y": 0, "curve": "stepped" },
					{ "time": 1.3333, "x": 0, "y": 0, "curve": "stepped" },
					{ "time": 2.6667, "x": 0, "y": 0 }
				],
				"scale": [
					{ "time": 0, "x": 1, "y": 1, "curve": "stepped" },
					{ "time": 1.3333, "x": 1, "y": 1, "curve": "stepped" },
					{ "time": 2.6667, "x": 1, "y": 1 }
				]
			},
			"aitehua_66": {
				"rotate": [
					{ "time": 0, "angle": 0, "curve": "stepped" },
					{ "time": 1.3333, "angle": 0, "curve": "stepped" },
					{ "time": 2.6667, "angle": 0 }
				],
				"translate": [
					{ "time": 0, "x": 0, "y": 0, "curve": "stepped" },
					{ "time": 1.3333, "x": 0, "y": 0, "curve": "stepped" },
					{ "time": 2.6667, "x": 0, "y": 0 }
				],
				"scale": [
					{ "time": 0, "x": 1, "y": 1, "curve": "stepped" },
					{ "time": 1.3333, "x": 1, "y": 1, "curve": "stepped" },
					{ "time": 2.6667, "x": 1, "y": 1 }
				]
			},
			"aitehua_64": {
				"rotate": [
					{ "time": 0, "angle": 0, "curve": "stepped" },
					{ "time": 1.3333, "angle": 0, "curve": "stepped" },
					{ "time": 2.6667, "angle": 0 }
				],
				"translate": [
					{ "time": 0, "x": 0, "y": 0, "curve": "stepped" },
					{ "time": 1.3333, "x": 0, "y": 0, "curve": "stepped" },
					{ "time": 2.6667, "x": 0, "y": 0 }
				],
				"scale": [
					{ "time": 0, "x": 1, "y": 1, "curve": "stepped" },
					{ "time": 1.3333, "x": 1, "y": 1, "curve": "stepped" },
					{ "time": 2.6667, "x": 1, "y": 1 }
				]
			},
			"aitehua_62": {
				"rotate": [
					{ "time": 0, "angle": 0, "curve": "stepped" },
					{ "time": 1.3333, "angle": 0, "curve": "stepped" },
					{ "time": 2.6667, "angle": 0 }
				],
				"translate": [
					{ "time": 0, "x": 0, "y": 0, "curve": "stepped" },
					{ "time": 1.3333, "x": 0, "y": 0, "curve": "stepped" },
					{ "time": 2.6667, "x": 0, "y": 0 }
				],
				"scale": [
					{ "time": 0, "x": 1, "y": 1, "curve": "stepped" },
					{ "time": 1.3333, "x": 1, "y": 1, "curve": "stepped" },
					{ "time": 2.6667, "x": 1, "y": 1 }
				]
			},
			"aitehua_67": {
				"rotate": [
					{ "time": 0, "angle": 0, "curve": "stepped" },
					{ "time": 1.3333, "angle": 0, "curve": "stepped" },
					{ "time": 2.6667, "angle": 0 }
				],
				"translate": [
					{ "time": 0, "x": 0, "y": 0, "curve": "stepped" },
					{ "time": 1.3333, "x": 0, "y": 0, "curve": "stepped" },
					{ "time": 2.6667, "x": 0, "y": 0 }
				],
				"scale": [
					{ "time": 0, "x": 1, "y": 1, "curve": "stepped" },
					{ "time": 1.3333, "x": 1, "y": 1, "curve": "stepped" },
					{ "time": 2.6667, "x": 1, "y": 1 }
				]
			},
			"aitehua_63": {
				"rotate": [
					{ "time": 0, "angle": 0, "curve": "stepped" },
					{ "time": 1.3333, "angle": 0, "curve": "stepped" },
					{ "time": 2.6667, "angle": 0 }
				],
				"translate": [
					{ "time": 0, "x": 0, "y": 0, "curve": "stepped" },
					{ "time": 1.3333, "x": 0, "y": 0, "curve": "stepped" },
					{ "time": 2.6667, "x": 0, "y": 0 }
				],
				"scale": [
					{ "time": 0, "x": 1, "y": 1, "curve": "stepped" },
					{ "time": 1.3333, "x": 1, "y": 1, "curve": "stepped" },
					{ "time": 2.6667, "x": 1, "y": 1 }
				]
			},
			"aitehua_65": {
				"rotate": [
					{ "time": 0, "angle": 0, "curve": "stepped" },
					{ "time": 1.3333, "angle": 0, "curve": "stepped" },
					{ "time": 2.6667, "angle": 0 }
				],
				"translate": [
					{ "time": 0, "x": 0, "y": 0, "curve": "stepped" },
					{ "time": 1.3333, "x": 0, "y": 0, "curve": "stepped" },
					{ "time": 2.6667, "x": 0, "y": 0 }
				],
				"scale": [
					{ "time": 0, "x": 1, "y": 1, "curve": "stepped" },
					{ "time": 1.3333, "x": 1, "y": 1, "curve": "stepped" },
					{ "time": 2.6667, "x": 1, "y": 1 }
				]
			}
		}
	},
	"win": {
		"slots": {
			"aitehua_50": {
				"attachment": [
					{ "time": 1.2667, "name": "aitehua_50" },
					{ "time": 1.3667, "name": "aitehua_51" }
				]
			},
			"aitehua_62": {
				"attachment": [
					{ "time": 0, "name": "aitehua_62" },
					{ "time": 1.3333, "name": "aitehua_62" }
				]
			},
			"aitehua_66": {
				"attachment": [
					{ "time": 0, "name": "aitehua_66" },
					{ "time": 1.3333, "name": "aitehua_66" }
				]
			}
		},
		"bones": {
			"aitehua_61": {
				"rotate": [
					{ "time": 0, "angle": 0, "curve": "stepped" },
					{ "time": 1.3333, "angle": 0, "curve": "stepped" },
					{ "time": 2.6667, "angle": 0 }
				],
				"translate": [
					{
						"time": 0,
						"x": 0,
						"y": 0,
						"curve": [ 0.25, 0, 0.75, 1 ]
					},
					{
						"time": 0.6667,
						"x": 0,
						"y": -2,
						"curve": [ 0.25, 0, 0.75, 1 ]
					},
					{
						"time": 1.3333,
						"x": 0,
						"y": 0,
						"curve": [ 0.25, 0, 0.75, 1 ]
					},
					{
						"time": 2,
						"x": 0,
						"y": -2,
						"curve": [ 0.25, 0, 0.75, 1 ]
					},
					{ "time": 2.6667, "x": 0, "y": 0 }
				],
				"scale": [
					{ "time": 0, "x": 1, "y": 1, "curve": "stepped" },
					{ "time": 1.3333, "x": 1, "y": 1, "curve": "stepped" },
					{ "time": 2.6667, "x": 1, "y": 1 }
				]
			},
			"aitehua_56": {
				"rotate": [
					{
						"time": 0,
						"angle": 0,
						"curve": [ 0.25, 0, 0.75, 1 ]
					},
					{
						"time": 0.6667,
						"angle": -0.68,
						"curve": [ 0.25, 0, 0.75, 1 ]
					},
					{
						"time": 1.3333,
						"angle": 0,
						"curve": [ 0.25, 0, 0.75, 1 ]
					},
					{
						"time": 2,
						"angle": -0.68,
						"curve": [ 0.25, 0, 0.75, 1 ]
					},
					{ "time": 2.6667, "angle": 0 }
				],
				"translate": [
					{ "time": 0, "x": 0, "y": 0, "curve": "stepped" },
					{ "time": 1.3333, "x": 0, "y": 0, "curve": "stepped" },
					{ "time": 2.6667, "x": 0, "y": 0 }
				],
				"scale": [
					{ "time": 0, "x": 1, "y": 1, "curve": "stepped" },
					{ "time": 1.3333, "x": 1, "y": 1, "curve": "stepped" },
					{ "time": 2.6667, "x": 1, "y": 1 }
				]
			},
			"aitehua_57": {
				"rotate": [
					{
						"time": 0,
						"angle": -0.41,
						"curve": [ 0.379, 0.6, 0.724, 1 ]
					},
					{
						"time": 0.1667,
						"angle": 0,
						"curve": [ 0.25, 0, 0.75, 1 ]
					},
					{
						"time": 0.8333,
						"angle": -2.24,
						"curve": [ 0.242, 0, 0.667, 0.67 ]
					},
					{
						"time": 1.3333,
						"angle": -0.41,
						"curve": [ 0.379, 0.6, 0.724, 1 ]
					},
					{
						"time": 1.5,
						"angle": 0,
						"curve": [ 0.25, 0, 0.75, 1 ]
					},
					{
						"time": 2.1667,
						"angle": -2.24,
						"curve": [ 0.242, 0, 0.667, 0.67 ]
					},
					{ "time": 2.6667, "angle": -0.41 }
				],
				"translate": [
					{
						"time": 0,
						"x": 0,
						"y": 0,
						"curve": [ 0.25, 0, 0.75, 1 ]
					},
					{
						"time": 0.6667,
						"x": -4.04,
						"y": 1.29,
						"curve": [ 0.25, 0, 0.75, 1 ]
					},
					{
						"time": 1.3333,
						"x": 0,
						"y": 0,
						"curve": [ 0.25, 0, 0.75, 1 ]
					},
					{
						"time": 2,
						"x": -4.04,
						"y": 1.29,
						"curve": [ 0.25, 0, 0.75, 1 ]
					},
					{ "time": 2.6667, "x": 0, "y": 0 }
				],
				"scale": [
					{ "time": 0, "x": 1, "y": 1, "curve": "stepped" },
					{ "time": 1.3333, "x": 1, "y": 1, "curve": "stepped" },
					{ "time": 2.6667, "x": 1, "y": 1 }
				]
			},
			"aitehua_59": {
				"rotate": [
					{ "time": 0, "angle": 0, "curve": "stepped" },
					{ "time": 1.3333, "angle": 0, "curve": "stepped" },
					{ "time": 2.6667, "angle": 0 }
				],
				"translate": [
					{ "time": 0, "x": 0, "y": 0, "curve": "stepped" },
					{ "time": 1.3333, "x": 0, "y": 0, "curve": "stepped" },
					{ "time": 2.6667, "x": 0, "y": 0 }
				],
				"scale": [
					{ "time": 0, "x": 1, "y": 1, "curve": "stepped" },
					{ "time": 1.3333, "x": 1, "y": 1, "curve": "stepped" },
					{ "time": 2.6667, "x": 1, "y": 1 }
				]
			},
			"aitehua_51": {
				"rotate": [
					{
						"time": 0,
						"angle": -3.18,
						"curve": [ 0.333, 0.33, 0.758, 1 ]
					},
					{
						"time": 0.5,
						"angle": 0,
						"curve": [ 0.25, 0, 0.75, 1 ]
					},
					{
						"time": 1.1667,
						"angle": -3.9,
						"curve": [ 0.25, 0, 1, 0.99 ]
					},
					{
						"time": 1.3333,
						"angle": -3.18,
						"curve": [ 0.333, 0.33, 0.758, 1 ]
					},
					{
						"time": 1.8333,
						"angle": 0,
						"curve": [ 0.25, 0, 0.75, 1 ]
					},
					{
						"time": 2.5,
						"angle": -3.9,
						"curve": [ 0.25, 0, 1, 0.99 ]
					},
					{ "time": 2.6667, "angle": -3.18 }
				],
				"translate": [
					{ "time": 0, "x": 0, "y": 0, "curve": "stepped" },
					{ "time": 1.3333, "x": 0, "y": 0, "curve": "stepped" },
					{ "time": 2.6667, "x": 0, "y": 0 }
				],
				"scale": [
					{ "time": 0, "x": 1, "y": 1, "curve": "stepped" },
					{ "time": 1.3333, "x": 1, "y": 1, "curve": "stepped" },
					{ "time": 2.6667, "x": 1, "y": 1 }
				]
			},
			"aitehua_48": {
				"rotate": [
					{
						"time": 0,
						"angle": 0.09,
						"curve": [ 0.375, 0.5, 0.75, 1 ]
					},
					{
						"time": 0.3333,
						"angle": -2.43,
						"curve": [ 0.25, 0, 0.75, 1 ]
					},
					{
						"time": 1,
						"angle": 2.61,
						"curve": [ 0.25, 0, 0.625, 0.5 ]
					},
					{
						"time": 1.3333,
						"angle": 0.09,
						"curve": [ 0.375, 0.5, 0.75, 1 ]
					},
					{
						"time": 1.6667,
						"angle": -2.43,
						"curve": [ 0.25, 0, 0.75, 1 ]
					},
					{
						"time": 2.3333,
						"angle": 2.61,
						"curve": [ 0.25, 0, 0.625, 0.5 ]
					},
					{ "time": 2.6667, "angle": 0.09 }
				],
				"translate": [
					{ "time": 0, "x": 0, "y": 0, "curve": "stepped" },
					{ "time": 1.3333, "x": 0, "y": 0, "curve": "stepped" },
					{ "time": 2.6667, "x": 0, "y": 0 }
				],
				"scale": [
					{ "time": 0, "x": 1, "y": 1, "curve": "stepped" },
					{ "time": 1.3333, "x": 1, "y": 1, "curve": "stepped" },
					{ "time": 2.6667, "x": 1, "y": 1 }
				]
			},
			"bone": {
				"rotate": [
					{
						"time": 0,
						"angle": 8.92,
						"curve": [ 0.333, 0.33, 0.758, 1 ]
					},
					{
						"time": 0.5,
						"angle": -8.93,
						"curve": [ 0.25, 0, 0.75, 1 ]
					},
					{
						"time": 1.1667,
						"angle": 12.96,
						"curve": [ 0.276, 0, 0.621, 0.4 ]
					},
					{
						"time": 1.3333,
						"angle": 8.92,
						"curve": [ 0.333, 0.33, 0.758, 1 ]
					},
					{
						"time": 1.8333,
						"angle": -8.93,
						"curve": [ 0.25, 0, 0.75, 1 ]
					},
					{
						"time": 2.5,
						"angle": 12.96,
						"curve": [ 0.276, 0, 0.621, 0.4 ]
					},
					{ "time": 2.6667, "angle": 8.92 }
				],
				"translate": [
					{ "time": 0, "x": 0, "y": 0, "curve": "stepped" },
					{ "time": 1.3333, "x": 0, "y": 0, "curve": "stepped" },
					{ "time": 2.6667, "x": 0, "y": 0 }
				],
				"scale": [
					{ "time": 0, "x": 1, "y": 1, "curve": "stepped" },
					{ "time": 1.3333, "x": 1, "y": 1, "curve": "stepped" },
					{ "time": 2.6667, "x": 1, "y": 1 }
				]
			},
			"aitehua_52": {
				"rotate": [
					{
						"time": 0,
						"angle": -4.44,
						"curve": [ 0, 0, 0.75, 1 ]
					},
					{
						"time": 0.5,
						"angle": 2.97,
						"curve": [ 0.25, 0, 0.75, 1 ]
					},
					{
						"time": 1.1667,
						"angle": -5.43,
						"curve": [ 0.299, 0, 0.636, 0.36 ]
					},
					{
						"time": 1.3333,
						"angle": -4.44,
						"curve": [ 0, 0, 0.75, 1 ]
					},
					{
						"time": 1.8333,
						"angle": 2.97,
						"curve": [ 0.25, 0, 0.75, 1 ]
					},
					{
						"time": 2.5,
						"angle": -5.43,
						"curve": [ 0.299, 0, 0.636, 0.36 ]
					},
					{ "time": 2.6667, "angle": -4.44 }
				],
				"translate": [
					{ "time": 0, "x": 0, "y": 0, "curve": "stepped" },
					{ "time": 1.3333, "x": 0, "y": 0, "curve": "stepped" },
					{ "time": 2.6667, "x": 0, "y": 0 }
				],
				"scale": [
					{ "time": 0, "x": 1, "y": 1, "curve": "stepped" },
					{ "time": 1.3333, "x": 1, "y": 1, "curve": "stepped" },
					{ "time": 2.6667, "x": 1, "y": 1 }
				]
			},
			"bone2": {
				"rotate": [
					{
						"time": 0,
						"angle": -2.72,
						"curve": [ 0, 0, 0.75, 1 ]
					},
					{
						"time": 0.1667,
						"angle": -10.62,
						"curve": [ 0.25, 0, 0.75, 1 ]
					},
					{
						"time": 0.8333,
						"angle": 13.38,
						"curve": [ 0.26, 0, 0.618, 0.44 ]
					},
					{
						"time": 1.3333,
						"angle": -2.72,
						"curve": [ 0, 0, 0.75, 1 ]
					},
					{
						"time": 1.5,
						"angle": -10.62,
						"curve": [ 0.25, 0, 0.75, 1 ]
					},
					{
						"time": 2.1667,
						"angle": 13.38,
						"curve": [ 0.26, 0, 0.618, 0.44 ]
					},
					{ "time": 2.6667, "angle": -2.72 }
				],
				"translate": [
					{ "time": 0, "x": 0, "y": 0, "curve": "stepped" },
					{ "time": 1.3333, "x": 0, "y": 0, "curve": "stepped" },
					{ "time": 2.6667, "x": 0, "y": 0 }
				],
				"scale": [
					{ "time": 0, "x": 1, "y": 1, "curve": "stepped" },
					{ "time": 1.3333, "x": 1, "y": 1, "curve": "stepped" },
					{ "time": 2.6667, "x": 1, "y": 1 }
				]
			},
			"aitehua_46": {
				"rotate": [
					{
						"time": 0,
						"angle": -0.65,
						"curve": [ 0.333, 0.33, 0.758, 1 ]
					},
					{
						"time": 0.5,
						"angle": 3.34,
						"curve": [ 0.25, 0, 0.75, 1 ]
					},
					{
						"time": 1.1667,
						"angle": -1.55,
						"curve": [ 0.276, 0, 0.621, 0.4 ]
					},
					{
						"time": 1.3333,
						"angle": -0.65,
						"curve": [ 0.333, 0.33, 0.758, 1 ]
					},
					{
						"time": 1.8333,
						"angle": 3.34,
						"curve": [ 0.25, 0, 0.75, 1 ]
					},
					{
						"time": 2.5,
						"angle": -1.55,
						"curve": [ 0.276, 0, 0.621, 0.4 ]
					},
					{ "time": 2.6667, "angle": -0.65 }
				],
				"translate": [
					{ "time": 0, "x": 0, "y": 0, "curve": "stepped" },
					{ "time": 1.3333, "x": 0, "y": 0, "curve": "stepped" },
					{ "time": 2.6667, "x": 0, "y": 0 }
				],
				"scale": [
					{ "time": 0, "x": 1, "y": 1, "curve": "stepped" },
					{ "time": 1.3333, "x": 1, "y": 1, "curve": "stepped" },
					{ "time": 2.6667, "x": 1, "y": 1 }
				]
			},
			"bone3": {
				"rotate": [
					{
						"time": 0,
						"angle": -4,
						"curve": [ 0.25, 0, 0.75, 1 ]
					},
					{
						"time": 0.6667,
						"angle": 3.84,
						"curve": [ 0.25, 0, 0.75, 1 ]
					},
					{
						"time": 1.3333,
						"angle": -4,
						"curve": [ 0.25, 0, 0.75, 1 ]
					},
					{
						"time": 2,
						"angle": 3.84,
						"curve": [ 0.25, 0, 0.75, 1 ]
					},
					{ "time": 2.6667, "angle": -4 }
				],
				"translate": [
					{ "time": 0, "x": 0, "y": 0, "curve": "stepped" },
					{ "time": 1.3333, "x": 0, "y": 0, "curve": "stepped" },
					{ "time": 2.6667, "x": 0, "y": 0 }
				],
				"scale": [
					{ "time": 0, "x": 1, "y": 1, "curve": "stepped" },
					{ "time": 1.3333, "x": 1, "y": 1, "curve": "stepped" },
					{ "time": 2.6667, "x": 1, "y": 1 }
				]
			},
			"bone4": {
				"rotate": [
					{
						"time": 0,
						"angle": -1.7,
						"curve": [ 0.329, 0.32, 0.664, 0.66 ]
					},
					{
						"time": 0.1667,
						"angle": -6.44,
						"curve": [ 0.25, 0, 0.75, 1 ]
					},
					{
						"time": 0.8333,
						"angle": 7.97,
						"curve": [ 0.26, 0, 0.618, 0.44 ]
					},
					{
						"time": 1.3333,
						"angle": -1.7,
						"curve": [ 0.329, 0.32, 0.664, 0.66 ]
					},
					{
						"time": 1.5,
						"angle": -6.44,
						"curve": [ 0.25, 0, 0.75, 1 ]
					},
					{
						"time": 2.1667,
						"angle": 7.97,
						"curve": [ 0.26, 0, 0.618, 0.44 ]
					},
					{ "time": 2.6667, "angle": -1.7 }
				],
				"translate": [
					{ "time": 0, "x": 0, "y": 0, "curve": "stepped" },
					{ "time": 1.3333, "x": 0, "y": 0, "curve": "stepped" },
					{ "time": 2.6667, "x": 0, "y": 0 }
				],
				"scale": [
					{ "time": 0, "x": 1, "y": 1, "curve": "stepped" },
					{ "time": 1.3333, "x": 1, "y": 1, "curve": "stepped" },
					{ "time": 2.6667, "x": 1, "y": 1 }
				]
			},
			"aitehua_47": {
				"rotate": [
					{
						"time": 0,
						"angle": 2.86,
						"curve": [ 0.25, 0, 0.75, 1 ]
					},
					{
						"time": 0.6667,
						"angle": -1.19,
						"curve": [ 0.25, 0, 0.75, 1 ]
					},
					{
						"time": 1.3333,
						"angle": 2.86,
						"curve": [ 0.25, 0, 0.75, 1 ]
					},
					{
						"time": 2,
						"angle": -1.19,
						"curve": [ 0.25, 0, 0.75, 1 ]
					},
					{ "time": 2.6667, "angle": 2.86 }
				],
				"translate": [
					{ "time": 0, "x": 0, "y": 0, "curve": "stepped" },
					{ "time": 1.3333, "x": 0, "y": 0, "curve": "stepped" },
					{ "time": 2.6667, "x": 0, "y": 0 }
				],
				"scale": [
					{ "time": 0, "x": 1, "y": 1, "curve": "stepped" },
					{ "time": 1.3333, "x": 1, "y": 1, "curve": "stepped" },
					{ "time": 2.6667, "x": 1, "y": 1 }
				]
			},
			"bone5": {
				"rotate": [
					{
						"time": 0,
						"angle": 5.94,
						"curve": [ 0.379, 0.6, 0.724, 1 ]
					},
					{
						"time": 0.1667,
						"angle": 8.12,
						"curve": [ 0.25, 0, 0.75, 1 ]
					},
					{
						"time": 0.8333,
						"angle": -3.73,
						"curve": [ 0.25, 0, 0.625, 0.5 ]
					},
					{
						"time": 1.3333,
						"angle": 5.94,
						"curve": [ 0.379, 0.6, 0.724, 1 ]
					},
					{
						"time": 1.5,
						"angle": 8.12,
						"curve": [ 0.25, 0, 0.75, 1 ]
					},
					{
						"time": 2.1667,
						"angle": -3.73,
						"curve": [ 0.25, 0, 0.625, 0.5 ]
					},
					{ "time": 2.6667, "angle": 5.94 }
				],
				"translate": [
					{ "time": 0, "x": 0, "y": 0, "curve": "stepped" },
					{ "time": 1.3333, "x": 0, "y": 0, "curve": "stepped" },
					{ "time": 2.6667, "x": 0, "y": 0 }
				],
				"scale": [
					{ "time": 0, "x": 1, "y": 1, "curve": "stepped" },
					{ "time": 1.3333, "x": 1, "y": 1, "curve": "stepped" },
					{ "time": 2.6667, "x": 1, "y": 1 }
				]
			},
			"bone6": {
				"rotate": [
					{
						"time": 0,
						"angle": 0.45,
						"curve": [ 0.375, 0.5, 0.75, 1 ]
					},
					{
						"time": 0.3333,
						"angle": 10.16,
						"curve": [ 0.25, 0, 0.75, 1 ]
					},
					{
						"time": 1,
						"angle": -9.26,
						"curve": [ 0.25, 0, 0.625, 0.5 ]
					},
					{
						"time": 1.3333,
						"angle": 0.45,
						"curve": [ 0.375, 0.5, 0.75, 1 ]
					},
					{
						"time": 1.6667,
						"angle": 10.16,
						"curve": [ 0.25, 0, 0.75, 1 ]
					},
					{
						"time": 2.3333,
						"angle": -9.26,
						"curve": [ 0.25, 0, 0.625, 0.5 ]
					},
					{ "time": 2.6667, "angle": 0.45 }
				],
				"translate": [
					{ "time": 0, "x": 0, "y": 0, "curve": "stepped" },
					{ "time": 1.3333, "x": 0, "y": 0, "curve": "stepped" },
					{ "time": 2.6667, "x": 0, "y": 0 }
				],
				"scale": [
					{ "time": 0, "x": 1, "y": 1, "curve": "stepped" },
					{ "time": 1.3333, "x": 1, "y": 1, "curve": "stepped" },
					{ "time": 2.6667, "x": 1, "y": 1 }
				]
			},
			"aitehua_55": {
				"rotate": [
					{
						"time": 0,
						"angle": -3.5,
						"curve": [ 0.379, 0.6, 0.724, 1 ]
					},
					{
						"time": 0.1667,
						"angle": -4.04,
						"curve": [ 0.25, 0, 0.75, 1 ]
					},
					{
						"time": 0.8333,
						"angle": 2.93,
						"curve": [ 0.242, 0, 0.667, 0.67 ]
					},
					{
						"time": 1.3333,
						"angle": -3.5,
						"curve": [ 0.379, 0.6, 0.724, 1 ]
					},
					{
						"time": 1.5,
						"angle": -4.04,
						"curve": [ 0.25, 0, 0.75, 1 ]
					},
					{
						"time": 2.1667,
						"angle": 2.93,
						"curve": [ 0.242, 0, 0.667, 0.67 ]
					},
					{ "time": 2.6667, "angle": -3.5 }
				],
				"translate": [
					{ "time": 0, "x": 0, "y": 0, "curve": "stepped" },
					{ "time": 1.3333, "x": 0, "y": 0, "curve": "stepped" },
					{ "time": 2.6667, "x": 0, "y": 0 }
				],
				"scale": [
					{ "time": 0, "x": 1, "y": 1, "curve": "stepped" },
					{ "time": 1.3333, "x": 1, "y": 1, "curve": "stepped" },
					{ "time": 2.6667, "x": 1, "y": 1 }
				]
			},
			"aitehua_54": {
				"rotate": [
					{
						"time": 0,
						"angle": -0.98,
						"curve": [ 0.379, 0.6, 0.724, 1 ]
					},
					{
						"time": 0.1667,
						"angle": 0,
						"curve": [ 0.25, 0, 0.75, 1 ]
					},
					{
						"time": 0.8333,
						"angle": -365.29,
						"curve": [ 0.242, 0, 0.667, 0.67 ]
					},
					{
						"time": 1.3333,
						"angle": -0.98,
						"curve": [ 0.379, 0.6, 0.724, 1 ]
					},
					{
						"time": 1.5,
						"angle": 0,
						"curve": [ 0.25, 0, 0.75, 1 ]
					},
					{
						"time": 2.1667,
						"angle": -365.29,
						"curve": [ 0.242, 0, 0.667, 0.67 ]
					},
					{ "time": 2.6667, "angle": -0.98 }
				],
				"translate": [
					{ "time": 0, "x": 0, "y": 0, "curve": "stepped" },
					{ "time": 1.3333, "x": 0, "y": 0, "curve": "stepped" },
					{ "time": 2.6667, "x": 0, "y": 0 }
				],
				"scale": [
					{ "time": 0, "x": 1, "y": 1, "curve": "stepped" },
					{ "time": 1.3333, "x": 1, "y": 1, "curve": "stepped" },
					{ "time": 2.6667, "x": 1, "y": 1 }
				]
			},
			"aitehua_53": {
				"rotate": [
					{
						"time": 0,
						"angle": -0.42,
						"curve": [ 0.351, 0.65, 0.686, 1 ]
					},
					{
						"time": 0.1667,
						"angle": 0,
						"curve": [ 0.25, 0, 0.75, 1 ]
					},
					{
						"time": 0.8333,
						"angle": -4.53,
						"curve": [ 0.25, 0, 1, 0.97 ]
					},
					{
						"time": 1.3333,
						"angle": -0.42,
						"curve": [ 0.351, 0.65, 0.686, 1 ]
					},
					{
						"time": 1.5,
						"angle": 0,
						"curve": [ 0.25, 0, 0.75, 1 ]
					},
					{
						"time": 2.1667,
						"angle": -4.53,
						"curve": [ 0.25, 0, 1, 0.97 ]
					},
					{ "time": 2.6667, "angle": -0.42 }
				],
				"translate": [
					{ "time": 0, "x": 0, "y": 0, "curve": "stepped" },
					{ "time": 1.3333, "x": 0, "y": 0, "curve": "stepped" },
					{ "time": 2.6667, "x": 0, "y": 0 }
				],
				"scale": [
					{ "time": 0, "x": 1, "y": 1, "curve": "stepped" },
					{ "time": 1.3333, "x": 1, "y": 1, "curve": "stepped" },
					{ "time": 2.6667, "x": 1, "y": 1 }
				]
			},
			"aitehua_58": {
				"rotate": [
					{
						"time": 0,
						"angle": -1.51,
						"curve": [ 0.379, 0.6, 0.724, 1 ]
					},
					{
						"time": 0.1667,
						"angle": 0,
						"curve": [ 0.25, 0, 0.75, 1 ]
					},
					{
						"time": 0.8333,
						"angle": -8.21,
						"curve": [ 0.242, 0, 0.667, 0.67 ]
					},
					{
						"time": 1.3333,
						"angle": -1.51,
						"curve": [ 0.379, 0.6, 0.724, 1 ]
					},
					{
						"time": 1.5,
						"angle": 0,
						"curve": [ 0.25, 0, 0.75, 1 ]
					},
					{
						"time": 2.1667,
						"angle": -8.21,
						"curve": [ 0.242, 0, 0.667, 0.67 ]
					},
					{ "time": 2.6667, "angle": -1.51 }
				],
				"translate": [
					{ "time": 0, "x": 0, "y": 0, "curve": "stepped" },
					{ "time": 1.3333, "x": 0, "y": 0, "curve": "stepped" },
					{ "time": 2.6667, "x": 0, "y": 0 }
				],
				"scale": [
					{ "time": 0, "x": 1, "y": 1, "curve": "stepped" },
					{ "time": 1.3333, "x": 1, "y": 1, "curve": "stepped" },
					{ "time": 2.6667, "x": 1, "y": 1 }
				]
			},
			"aitehua_45": {
				"rotate": [
					{
						"time": 0,
						"angle": 1.73,
						"curve": [ 0.379, 0.6, 0.724, 1 ]
					},
					{
						"time": 0.1667,
						"angle": 0,
						"curve": [ 0.25, 0, 0.75, 1 ]
					},
					{
						"time": 0.8333,
						"angle": 9.37,
						"curve": [ 0.242, 0, 0.667, 0.67 ]
					},
					{
						"time": 1.3333,
						"angle": 1.73,
						"curve": [ 0.379, 0.6, 0.724, 1 ]
					},
					{
						"time": 1.5,
						"angle": 0,
						"curve": [ 0.25, 0, 0.75, 1 ]
					},
					{
						"time": 2.1667,
						"angle": 9.37,
						"curve": [ 0.242, 0, 0.667, 0.67 ]
					},
					{ "time": 2.6667, "angle": 1.73 }
				],
				"translate": [
					{ "time": 0, "x": 0, "y": 0, "curve": "stepped" },
					{ "time": 1.3333, "x": 0, "y": 0, "curve": "stepped" },
					{ "time": 2.6667, "x": 0, "y": 0 }
				],
				"scale": [
					{ "time": 0, "x": 1, "y": 1, "curve": "stepped" },
					{ "time": 1.3333, "x": 1, "y": 1, "curve": "stepped" },
					{ "time": 2.6667, "x": 1, "y": 1 }
				]
			},
			"aitehua_44": {
				"rotate": [
					{
						"time": 0,
						"angle": 0.62,
						"curve": [ 0.379, 0.6, 0.724, 1 ]
					},
					{
						"time": 0.1667,
						"angle": 0,
						"curve": [ 0.25, 0, 0.75, 1 ]
					},
					{
						"time": 0.8333,
						"angle": 3.37,
						"curve": [ 0.242, 0, 0.667, 0.67 ]
					},
					{
						"time": 1.3333,
						"angle": 0.62,
						"curve": [ 0.379, 0.6, 0.724, 1 ]
					},
					{
						"time": 1.5,
						"angle": 0,
						"curve": [ 0.25, 0, 0.75, 1 ]
					},
					{
						"time": 2.1667,
						"angle": 3.37,
						"curve": [ 0.242, 0, 0.667, 0.67 ]
					},
					{ "time": 2.6667, "angle": 0.62 }
				],
				"translate": [
					{ "time": 0, "x": 0, "y": 0, "curve": "stepped" },
					{ "time": 1.3333, "x": 0, "y": 0, "curve": "stepped" },
					{ "time": 2.6667, "x": 0, "y": 0 }
				],
				"scale": [
					{ "time": 0, "x": 1, "y": 1, "curve": "stepped" },
					{ "time": 1.3333, "x": 1, "y": 1, "curve": "stepped" },
					{ "time": 2.6667, "x": 1, "y": 1 }
				]
			},
			"aitehua_66": {
				"rotate": [
					{ "time": 0, "angle": 0, "curve": "stepped" },
					{ "time": 1.3333, "angle": 0, "curve": "stepped" },
					{ "time": 2.6667, "angle": 0 }
				],
				"translate": [
					{ "time": 0, "x": 0, "y": 0, "curve": "stepped" },
					{ "time": 1.3333, "x": 0, "y": 0, "curve": "stepped" },
					{ "time": 2.6667, "x": 0, "y": 0 }
				],
				"scale": [
					{ "time": 0, "x": 1, "y": 1, "curve": "stepped" },
					{ "time": 1.3333, "x": 1, "y": 1, "curve": "stepped" },
					{ "time": 2.6667, "x": 1, "y": 1 }
				]
			},
			"aitehua_64": {
				"rotate": [
					{ "time": 0, "angle": 0, "curve": "stepped" },
					{ "time": 1.3333, "angle": 0, "curve": "stepped" },
					{ "time": 2.6667, "angle": 0 }
				],
				"translate": [
					{ "time": 0, "x": 0, "y": 0, "curve": "stepped" },
					{ "time": 1.3333, "x": 0, "y": 0, "curve": "stepped" },
					{ "time": 2.6667, "x": 0, "y": 0 }
				],
				"scale": [
					{ "time": 0, "x": 1, "y": 1, "curve": "stepped" },
					{ "time": 1.3333, "x": 1, "y": 1, "curve": "stepped" },
					{ "time": 2.6667, "x": 1, "y": 1 }
				]
			},
			"aitehua_62": {
				"rotate": [
					{ "time": 0, "angle": 0, "curve": "stepped" },
					{ "time": 1.3333, "angle": 0, "curve": "stepped" },
					{ "time": 2.6667, "angle": 0 }
				],
				"translate": [
					{ "time": 0, "x": 0, "y": 0, "curve": "stepped" },
					{ "time": 1.3333, "x": 0, "y": 0, "curve": "stepped" },
					{ "time": 2.6667, "x": 0, "y": 0 }
				],
				"scale": [
					{ "time": 0, "x": 1, "y": 1, "curve": "stepped" },
					{ "time": 1.3333, "x": 1, "y": 1, "curve": "stepped" },
					{ "time": 2.6667, "x": 1, "y": 1 }
				]
			},
			"aitehua_67": {
				"rotate": [
					{ "time": 0, "angle": 0, "curve": "stepped" },
					{ "time": 1.3333, "angle": 0, "curve": "stepped" },
					{ "time": 2.6667, "angle": 0 }
				],
				"translate": [
					{ "time": 0, "x": 0, "y": 0, "curve": "stepped" },
					{ "time": 1.3333, "x": 0, "y": 0, "curve": "stepped" },
					{ "time": 2.6667, "x": 0, "y": 0 }
				],
				"scale": [
					{ "time": 0, "x": 1, "y": 1, "curve": "stepped" },
					{ "time": 1.3333, "x": 1, "y": 1, "curve": "stepped" },
					{ "time": 2.6667, "x": 1, "y": 1 }
				]
			},
			"aitehua_63": {
				"rotate": [
					{ "time": 0, "angle": 0, "curve": "stepped" },
					{ "time": 1.3333, "angle": 0, "curve": "stepped" },
					{ "time": 2.6667, "angle": 0 }
				],
				"translate": [
					{ "time": 0, "x": 0, "y": 0, "curve": "stepped" },
					{ "time": 1.3333, "x": 0, "y": 0, "curve": "stepped" },
					{ "time": 2.6667, "x": 0, "y": 0 }
				],
				"scale": [
					{ "time": 0, "x": 1, "y": 1, "curve": "stepped" },
					{ "time": 1.3333, "x": 1, "y": 1, "curve": "stepped" },
					{ "time": 2.6667, "x": 1, "y": 1 }
				]
			},
			"aitehua_65": {
				"rotate": [
					{ "time": 0, "angle": 0, "curve": "stepped" },
					{ "time": 1.3333, "angle": 0, "curve": "stepped" },
					{ "time": 2.6667, "angle": 0 }
				],
				"translate": [
					{ "time": 0, "x": 0, "y": 0, "curve": "stepped" },
					{ "time": 1.3333, "x": 0, "y": 0, "curve": "stepped" },
					{ "time": 2.6667, "x": 0, "y": 0 }
				],
				"scale": [
					{ "time": 0, "x": 1, "y": 1, "curve": "stepped" },
					{ "time": 1.3333, "x": 1, "y": 1, "curve": "stepped" },
					{ "time": 2.6667, "x": 1, "y": 1 }
				]
			}
		}
	}
}
}