{"skeleton":{"hash":"i+VzUOioXemFEpAKvpmFoWAJVxw","spine":"3.5.35","width":0,"height":0},"bones":[{"name":"root"},{"name":"bone","parent":"root"},{"name":"bone2","parent":"bone"},{"name":"bone3","parent":"bone","scaleX":1.4,"scaleY":1.4},{"name":"bone4","parent":"bone"},{"name":"bone5","parent":"bone4"},{"name":"bone6","parent":"bone4","rotation":484.8},{"name":"bone7","parent":"bone"}],"slots":[{"name":"images/quanyuz","bone":"bone2"},{"name":"images/quanyuz_0000","bone":"bone3"},{"name":"images/holo_quan","bone":"bone5","blend":"screen"},{"name":"images/holo_quan2","bone":"bone6","blend":"screen"},{"name":"images/2204c87ebc","bone":"bone7","blend":"additive"}],"skins":{"default":{"images/2204c87ebc":{"images/2204c87ebc":{"width":128,"height":128}},"images/holo_quan":{"images/holo_quan":{"width":256,"height":256}},"images/holo_quan2":{"images/holo_quan":{"width":256,"height":256}},"images/quanyuz":{"images/quanyuz":{"type":"mesh","uvs":[0.86338,0.99999,0.99999,0.83161,0.99999,0.50886,1,0.10779,0.83091,0,0.27795,1.0E-5,1.0E-5,0.09302,1.0E-5,0.41633,1.0E-5,0.60822,1.0E-5,0.86259,0.23049,1,0.4618,0.85065,0.24866,0.63649,0.29372,0.27141,0.48624,0.14903,0.71563,0.26529,0.69951,0.58064,0.646,0.8017,0.49444,0.52636,0.54359,0.36523,0.35516,0.73031,0.62961,0.71604,0.32649,0.44681,0.76069,0.41622,0.40148,0.87253,0.2848,0.80848,0.22497,0.71613,0.21001,0.61632,0.1801,0.44651,0.17411,0.27968,0.26386,0.16498,0.45233,0.10242,0.67072,0.13221,0.7515,0.22903,0.7874,0.34522,0.81432,0.48822,0.76645,0.71464,0.67371,0.85466,0.52712,0.91424,0.81151,0.59938],"triangles":[31,5,4,32,31,4,14,31,32,30,6,5,30,5,31,33,32,4,33,4,3,15,32,33,13,30,31,13,31,14,29,6,30,29,30,13,34,33,3,15,33,34,15,19,14,15,14,32,13,14,19,23,15,34,19,15,23,7,6,29,28,29,13,7,29,28,22,13,19,28,13,22,2,35,34,23,34,35,3,2,34,18,22,19,16,19,23,16,23,35,18,19,16,39,16,35,39,35,2,8,7,28,27,28,22,8,28,27,12,27,22,12,22,18,36,16,39,21,18,16,21,16,36,26,27,12,20,12,18,20,18,21,26,12,20,17,21,36,25,26,20,1,39,2,36,39,1,11,20,21,11,21,17,24,25,20,37,17,36,26,9,8,26,8,27,9,26,25,11,24,20,38,11,17,38,17,37,0,36,1,37,36,0,10,9,25,10,25,24,38,10,24,38,24,11,38,37,0,10,38,0],"vertices":[-87.22,241.4,-119.29,160.34,-118.18,5.42,-116.79,-187.08,-76.01,-238.53,56.14,-237.58,122.25,-192.46,121.13,-37.27,120.47,54.83,119.59,176.93,64.03,242.49,9.27,170.4,60.95,67.98,51.44,-107.34,5.85,-166.4,-49.37,-111,-46.61,40.39,-34.58,146.59,2.59,14.69,-8.6,-62.73,35.17,112.83,-30.37,105.5,43,-23.2,-60.66,-38.63,23.61,181.01,51.72,150.47,66.33,106.24,70.25,58.36,77.99,-23.09,80,-103.16,58.94,-158.37,14.11,-188.72,-38.18,-174.8,-57.82,-128.46,-66.8,-72.76,-73.73,-4.16,-63.07,104.6,-41.39,171.96,-6.56,200.81,-73.44,49.19],"hull":11}},"images/quanyuz_0000":{"images/quanyuz_0000":{"width":168,"height":415},"images/quanyuz_0001":{"width":168,"height":415},"images/quanyuz_0003":{"width":168,"height":415},"images/quanyuz_0005":{"width":168,"height":415},"images/quanyuz_0007":{"width":168,"height":415},"images/quanyuz_0009":{"width":168,"height":415}}}},"events":{"qishou_21_4_1":{},"qishou_21_4_2":{},"qishou_21_4_3":{},"qishou_21_4_4":{}},"animations":{"animation_0":{"slots":{"images/2204c87ebc":{"color":[{"time":0,"color":"c690ffff","curve":"stepped"},{"time":0.0667,"color":"c690ffff","curve":[0.481,0.22,0.454,0.74]},{"time":0.2,"color":"c690ff62","curve":[0.481,0.22,0.454,0.74]},{"time":0.4,"color":"c690ff47","curve":[0.481,0.22,0.454,0.74]},{"time":0.6,"color":"c690ff62","curve":[0.481,0.22,0.454,0.74]},{"time":0.8,"color":"c690ff47","curve":[0.481,0.22,0.454,0.74]},{"time":1.0667,"color":"c690ff00"}],"attachment":[{"time":0,"name":"images/2204c87ebc"}]},"images/holo_quan":{"color":[{"time":0,"color":"ffffff00","curve":[0.481,0.22,0.454,0.74]},{"time":0.0667,"color":"ffffffff","curve":"stepped"},{"time":0.8333,"color":"ffffffff","curve":[0.481,0.22,0.454,0.74]},{"time":1.0667,"color":"ffffff00"}],"attachment":[{"time":0,"name":"images/holo_quan"}]},"images/holo_quan2":{"color":[{"time":0,"color":"ffffff00","curve":[0.481,0.22,0.454,0.74]},{"time":0.0667,"color":"ffffffc6","curve":"stepped"},{"time":0.8333,"color":"ffffffc6","curve":[0.481,0.22,0.454,0.74]},{"time":1.0667,"color":"ffffff00"}],"attachment":[{"time":0,"name":"images/holo_quan"}]},"images/quanyuz":{"color":[{"time":0,"color":"ffffff30","curve":[0.361,0.3,0.693,0.64]},{"time":0.0667,"color":"ffffffff","curve":"stepped"},{"time":0.8667,"color":"ffffffff","curve":[0.137,0.35,0.425,0.85]},{"time":1.0667,"color":"ffffff00"}],"attachment":[{"time":0,"name":"images/quanyuz"}]},"images/quanyuz_0000":{"color":[{"time":0,"color":"ffffff31","curve":[0.361,0.3,0.693,0.64]},{"time":0.0667,"color":"ffffffff","curve":"stepped"},{"time":0.8667,"color":"ffffffff","curve":[0.481,0.22,0.454,0.74]},{"time":1.0667,"color":"ffffff00"}],"attachment":[{"time":0,"name":"images/quanyuz_0009"},{"time":0.0667,"name":"images/quanyuz_0001"},{"time":0.1333,"name":"images/quanyuz_0003"},{"time":0.1667,"name":"images/quanyuz_0005"},{"time":0.2333,"name":"images/quanyuz_0007"},{"time":0.3,"name":"images/quanyuz_0009"},{"time":0.3667,"name":"images/quanyuz_0000"},{"time":0.4333,"name":"images/quanyuz_0001"},{"time":0.4667,"name":"images/quanyuz_0003"},{"time":0.5333,"name":"images/quanyuz_0005"},{"time":0.6,"name":"images/quanyuz_0007"},{"time":0.6667,"name":"images/quanyuz_0009"},{"time":0.7,"name":"images/quanyuz_0000"},{"time":0.7667,"name":"images/quanyuz_0001"},{"time":0.8333,"name":"images/quanyuz_0003"},{"time":0.9,"name":"images/quanyuz_0005"},{"time":0.9667,"name":"images/quanyuz_0007"},{"time":1,"name":"images/quanyuz_0009"},{"time":1.0667,"name":"images/quanyuz_0000"}]}},"bones":{"bone":{"translate":[{"time":0,"x":0,"y":0,"curve":[0.235,0.6,0.62,0.9]},{"time":0.1667,"x":88.4,"y":0},{"time":0.3333,"x":162,"y":10},{"time":0.5,"x":162,"y":-10},{"time":0.6667,"x":162,"y":10},{"time":0.8333,"x":162,"y":0}],"scale":[{"time":0,"x":0.48,"y":4.326,"curve":[0.196,0.32,0.516,0.67]},{"time":0.0333,"x":1.966,"y":4.572,"curve":[0.244,0.4,0.57,0.76]},{"time":0.0667,"x":3.8,"y":4.5,"curve":"stepped"},{"time":0.8667,"x":3.8,"y":4.5}],"shear":[{"time":0,"x":0,"y":0}]},"bone3":{"scale":[{"time":0,"x":0.966,"y":0.929}]},"bone5":{"rotate":[{"time":0,"angle":0},{"time":1.0667,"angle":-117.16}]},"bone4":{"scale":[{"time":0,"x":2.47,"y":2.635}]},"bone6":{"rotate":[{"time":0,"angle":-289.14,"curve":[0.481,0.22,0.454,0.74]},{"time":1.0667,"angle":-347.7}],"scale":[{"time":0,"x":0.609,"y":0.632}]},"bone7":{"scale":[{"time":0,"x":4.213,"y":5.175}]},"root":{"translate":[{"time":0,"x":-162,"y":240}]}},"deform":{"default":{"images/quanyuz":{"images/quanyuz":[{"time":0,"offset":25,"vertices":[-0.69145],"curve":[0.293,0.12,0.562,0.84]},{"time":0.2,"offset":23,"vertices":[-4.02713,-4.53233,13.00095,-9.06479,6.44345,6.34536,8.85982,-2.71944,-11.27608,-6.5928,-4.24706,8.15833,0,2.43705,-6.49609,2.71945,3.22176,-8.34654,4.16341,0,0,5.6864,5.77433,2.71942],"curve":[0.293,0.12,0.562,0.84]},{"time":0.4667,"offset":22,"vertices":[3.26768,-1.84956,-4.53233,5.01657,-9.88168,13.70198,21.86672,5.95642,9.53426,-15.6312,-6.5928,3.73734,12.24289,6.53268,11.42317,-7.22195,10.88872,5.39932,-12.43102,-6.72436,0,0,5.6864,5.77433,11.70549,-2.90342],"curve":[0.293,0.12,0.562,0.84]},{"time":0.7667,"offset":2,"vertices":[1.63379,0,1.63379,0,0,0,0,0,0,0,0,0,0,0,-10.61987,1.45167,0,0,0,0,-0.81689,-9.10813,-4.53227,3.56486,-18.86774,20.96048,37.38806,7.40808,15.25266,-18.53462,-0.87439,0.8339,17.96124,2.0E-5,2.43716,-8.67366,10.88872,5.39932,-17.33247,-8.17606,-2.45076,1.45171,-4.11648,5.77433,7.62099,-7.98442],"curve":[0.293,0.12,0.562,0.84]},{"time":1.0667,"offset":23,"vertices":[-4.02713,-4.53233,13.00095,-9.06479,6.44345,6.34536,8.85982,-2.71944,-11.27608,-6.5928,-4.24706,8.15833,0,2.43705,-6.49609,2.71945,3.22176,-8.34654,4.16341,0,0,5.6864,5.77433,2.71942]}]}}},"events":[{"time":0.1667,"name":"qishou_21_4_4"},{"time":0.4,"name":"qishou_21_4_3"},{"time":0.6,"name":"qishou_21_4_2"},{"time":0.8333,"name":"qishou_21_4_1"}]}}}